Workbook
Name lst_years: '📚 Справочник'!$A$5:$A$9
Name lst_months: '📚 Справочник'!$B$5:$B$16
Name lst_cats: '📚 Справочник'!$D$5:$D$29
Name lst_cat_wish: '📚 Справочник'!$E$5:$E$29
Name lst_exp_items: '📚 Справочник'!$H$5:$H$104
Name lst_inc_types: '📚 Справочник'!$J$5:$J$24
Name lst_inc_items: '📚 Справочник'!$L$5:$L$104
Name lst_exp_status: '📚 Справочник'!$N$5:$N$8
Name lst_inc_status: '📚 Справочник'!$O$5:$O$7
Name lst_priority: '📚 Справочник'!$Q$5:$Q$7
Name exp_year: '💸 Расходы'!$A$5:$A$504
Name exp_month: '💸 Расходы'!$B$5:$B$504
Name exp_item: '💸 Расходы'!$C$5:$C$504
Name exp_cat: '💸 Расходы'!$D$5:$D$504
Name exp_desc: '💸 Расходы'!$E$5:$E$504
Name exp_prio: '💸 Расходы'!$F$5:$F$504
Name exp_plan: '💸 Расходы'!$G$5:$G$504
Name exp_fact: '💸 Расходы'!$H$5:$H$504
Name exp_status: '💸 Расходы'!$J$5:$J$504
Name exp_wishno: '💸 Расходы'!$L$5:$L$504
Name inc_year: '💰 Доходы'!$A$5:$A$304
Name inc_month: '💰 Доходы'!$B$5:$B$304
Name inc_type: '💰 Доходы'!$D$5:$D$304
Name inc_plan: '💰 Доходы'!$F$5:$F$304
Name inc_fact: '💰 Доходы'!$G$5:$G$304
Name inc_status: '💰 Доходы'!$I$5:$I$304

Sheet 🏠 Главная
A1: 🏠 Финансовый план 2026 – 2030
A2: Личный планер доходов и расходов: план vs факт по месяцам и годам, хотелки и мечты.
B4: 📌 Итого за 2026–2030 | G4: 🗓 Текущий месяц | I4: =INDEX(lst_months,MONTH(TODAY()))&" "&YEAR(TODAY())
C5: 📝 ПЛАН | D5: ✅ ФАКТ | E5: % выполнения | H5: 📝 ПЛАН | I5: ✅ ФАКТ | J5: % выполнения
B6: 💰 Доходы | C6: ='📊 По годам'!B10 | D6: ='📊 По годам'!C10 | E6: =IF(C6=0,"",D6/C6) | G6: 💰 Доходы | H6: =IFERROR(INDEX('📅 По месяцам'!$D$5:$D$64,((YEAR(TODAY())-2026)*12+MONTH(TODAY()))),0) | I6: =IFERROR(INDEX('📅 По месяцам'!$E$5:$E$64,((YEAR(TODAY())-2026)*12+MONTH(TODAY()))),0) | J6: =IF(H6=0,"",I6/H6)
B7: 💸 Расходы | C7: ='📊 По годам'!E10 | D7: ='📊 По годам'!F10 | E7: =IF(C7=0,"",D7/C7) | G7: 💸 Расходы | H7: =IFERROR(INDEX('📅 По месяцам'!$G$5:$G$64,((YEAR(TODAY())-2026)*12+MONTH(TODAY()))),0) | I7: =IFERROR(INDEX('📅 По месяцам'!$H$5:$H$64,((YEAR(TODAY())-2026)*12+MONTH(TODAY()))),0) | J7: =IF(H7=0,"",I7/H7)
B8: ⚖️ Остаток | C8: ='📊 По годам'!H10 | D8: ='📊 По годам'!I10 | E8: =IF(C8=0,"",D8/C8) | G8: ⚖️ Остаток | H8: =IFERROR(INDEX('📅 По месяцам'!$J$5:$J$64,((YEAR(TODAY())-2026)*12+MONTH(TODAY()))),0) | I8: =IFERROR(INDEX('📅 По месяцам'!$K$5:$K$64,((YEAR(TODAY())-2026)*12+MONTH(TODAY()))),0) | J8: =IF(H8=0,"",I8/H8)
B10: ✨ Хотелки | G10: 🧭 Навигация
C11: Всего | D11: Исполнено | E11: Прогресс | G11: 💸 Расходы | H11: вносить траты (план и факт)
C12: ='✨ Хотелки'!B4 | D12: ='✨ Хотелки'!C4 | E12: ='✨ Хотелки'!D4 | G12: 💰 Доходы | H12: вносить доходы (план и факт)
G13: 📅 По месяцам | H13: сводка по месяцам + графики
G14: 📊 По годам | H14: сводка по годам и категориям
G15: ✨ Хотелки | H15: список хотелок и мечт
G16: 📚 Справочник | H16: справочник для выпадающих списков
B18: 🎨 Как пользоваться
B19: ПЛАН | C19: 📝 ПЛАН — синие колонки. Заполняете заранее: сколько собираетесь потратить / потенциально заработать.
B20: ФАКТ | C20: ✅ ФАКТ — зелёные колонки. Заполняете по факту: сколько реально потратили / получили.
B21: ввод | C21: Жёлтые ячейки в «Справочнике» — ваши статьи, категории и типы дохода. Синий шрифт = ввод вручную.
B22: зачёркнуто | C22: Статус «✅ Выполнено» / «✅ Получено» автоматически зачёркивает строку (и хотелку в списке).
B23: сейчас | C23: Жёлтая строка в «По месяцам» — текущий месяц. Красный шрифт — перерасход или минус.
C24: Листы «По месяцам», «По годам», «Хотелки» и «Главная» считаются сами — в них ничего вводить не нужно.
C25: В листах «Расходы» и «Доходы» есть строки-ПРИМЕРЫ — замените или удалите их.

Sheet 💸 Расходы
A1: 💸 Расходы — план и факт
A2: Одна строка = одна трата. Синяя колонка «ПЛАН» — сколько собираетесь потратить, зелёная «ФАКТ» — сколько реально ушло. Статус «✅ Выполнено» зачёркивает строку. Год, месяц, статья, категория — из списков.
F3: Σ видимых → | G3: =SUBTOTAL(9,G5:G504) | H3: =SUBTOTAL(9,H5:H504)
A4: 📆 Год | B4: 🗓 Месяц | C4: 📝 Статья | D4: 🏷 Категория | E4: ✏️ Описание | F4: 🎯 Приоритет | G4: 📝 ПЛАН, ₸ | H4: ✅ ФАКТ, ₸ | I4: ± Разница (план − факт) | J4: 🚦 Статус | K4: 💬 Комментарий | L4: служ. №хотелки
A5: 2026 | B5: Октябрь | C5: Продукты | D5: 🛒 Нужда | E5: Продукты на месяц | F5: 🔥 Высокий | G5: 120000 | H5: 131500 | I5: =IF(OR(G5="",H5=""),"",G5-H5) | J5: ✅ Выполнено | L5: =IF(IFERROR(INDEX(lst_cat_wish,MATCH(D5,lst_cats,0))="Да",FALSE),MAX($L$4:L4)+1,"")
A6: 2026 | B6: Октябрь | C6: Аренда / ипотека | D6: 🧾 Обязательный платёж | E6: Аренда квартиры | F6: 🔥 Высокий | G6: 250000 | H6: 250000 | I6: =IF(OR(G6="",H6=""),"",G6-H6) | J6: ✅ Выполнено | L6: =IF(IFERROR(INDEX(lst_cat_wish,MATCH(D6,lst_cats,0))="Да",FALSE),MAX($L$4:L5)+1,"")
A7: 2026 | B7: Октябрь | C7: Подушка безопасности | D7: 🏦 Накопление | E7: 10% от дохода | F7: ⭐ Средний | G7: 60000 | H7: 60000 | I7: =IF(OR(G7="",H7=""),"",G7-H7) | J7: ✅ Выполнено | L7: =IF(IFERROR(INDEX(lst_cat_wish,MATCH(D7,lst_cats,0))="Да",FALSE),MAX($L$4:L6)+1,"")
A8: 2026 | B8: Октябрь | C8: Техника | D8: 🍭 Хотелка | E8: Беспроводные наушники | F8: ⭐ Средний | G8: 45000 | H8: 42000 | I8: =IF(OR(G8="",H8=""),"",G8-H8) | J8: ✅ Выполнено | L8: =IF(IFERROR(INDEX(lst_cat_wish,MATCH(D8,lst_cats,0))="Да",FALSE),MAX($L$4:L7)+1,"")
A9: 2026 | B9: Ноябрь | C9: Продукты | D9: 🛒 Нужда | E9: Продукты на месяц | F9: 🔥 Высокий | G9: 120000 | I9: =IF(OR(G9="",H9=""),"",G9-H9) | J9: ⏳ Запланировано | L9: =IF(IFERROR(INDEX(lst_cat_wish,MATCH(D9,lst_cats,0))="Да",FALSE),MAX($L$4:L8)+1,"")
A10: 2026 | B10: Ноябрь | C10: Аренда / ипотека | D10: 🧾 Обязательный платёж | E10: Аренда квартиры | F10: 🔥 Высокий | G10: 250000 | I10: =IF(OR(G10="",H10=""),"",G10-H10) | J10: ⏳ Запланировано | L10: =IF(IFERROR(INDEX(lst_cat_wish,MATCH(D10,lst_cats,0))="Да",FALSE),MAX($L$4:L9)+1,"")
A11: 2026 | B11: Декабрь | C11: Подарки | D11: 🎁 Подарок | E11: Новогодние подарки семье | F11: ⭐ Средний | G11: 80000 | I11: =IF(OR(G11="",H11=""),"",G11-H11) | J11: ⏳ Запланировано | L11: =IF(IFERROR(INDEX(lst_cat_wish,MATCH(D11,lst_cats,0))="Да",FALSE),MAX($L$4:L10)+1,"")
A12: 2027 | B12: Март | C12: Одежда | D12: 💫 Желание | E12: Новое пальто | F12: 💤 Низкий | G12: 90000 | I12: =IF(OR(G12="",H12=""),"",G12-H12) | J12: ⏳ Запланировано | L12: =IF(IFERROR(INDEX(lst_cat_wish,MATCH(D12,lst_cats,0))="Да",FALSE),MAX($L$4:L11)+1,"")
A13: 2027 | B13: Июль | C13: Путешествия | D13: 🌟 Мечта | E13: Отпуск в Грузии | F13: 🔥 Высокий | G13: 600000 | I13: =IF(OR(G13="",H13=""),"",G13-H13) | J13: ⏳ Запланировано | L13: =IF(IFERROR(INDEX(lst_cat_wish,MATCH(D13,lst_cats,0))="Да",FALSE),MAX($L$4:L12)+1,"")
A14: 2028 | B14: Май | C14: Курсы | D14: 🎓 Образование | E14: Курс английского | F14: ⭐ Средний | G14: 150000 | I14: =IF(OR(G14="",H14=""),"",G14-H14) | J14: ⏳ Запланировано | L14: =IF(IFERROR(INDEX(lst_cat_wish,MATCH(D14,lst_cats,0))="Да",FALSE),MAX($L$4:L13)+1,"")
I15: =IF(OR(G15="",H15=""),"",G15-H15) | L15: =IF(IFERROR(INDEX(lst_cat_wish,MATCH(D15,lst_cats,0))="Да",FALSE),MAX($L$4:L14)+1,"")
I16: =IF(OR(G16="",H16=""),"",G16-H16) | L16: =IF(IFERROR(INDEX(lst_cat_wish,MATCH(D16,lst_cats,0))="Да",FALSE),MAX($L$4:L15)+1,"")
I17: =IF(OR(G17="",H17=""),"",G17-H17) | L17: =IF(IFERROR(INDEX(lst_cat_wish,MATCH(D17,lst_cats,0))="Да",FALSE),MAX($L$4:L16)+1,"")
I18: =IF(OR(G18="",H18=""),"",G18-H18) | L18: =IF(IFERROR(INDEX(lst_cat_wish,MATCH(D18,lst_cats,0))="Да",FALSE),MAX($L$4:L17)+1,"")
I19: =IF(OR(G19="",H19=""),"",G19-H19) | L19: =IF(IFERROR(INDEX(lst_cat_wish,MATCH(D19,lst_cats,0))="Да",FALSE),MAX($L$4:L18)+1,"")
I20: =IF(OR(G20="",H20=""),"",G20-H20) | L20: =IF(IFERROR(INDEX(lst_cat_wish,MATCH(D20,lst_cats,0))="Да",FALSE),MAX($L$4:L19)+1,"")
I21: =IF(OR(G21="",H21=""),"",G21-H21) | L21: =IF(IFERROR(INDEX(lst_cat_wish,MATCH(D21,lst_cats,0))="Да",FALSE),MAX($L$4:L20)+1,"")
I22: =IF(OR(G22="",H22=""),"",G22-H22) | L22: =IF(IFERROR(INDEX(lst_cat_wish,MATCH(D22,lst_cats,0))="Да",FALSE),MAX($L$4:L21)+1,"")
I23: =IF(OR(G23="",H23=""),"",G23-H23) | L23: =IF(IFERROR(INDEX(lst_cat_wish,MATCH(D23,lst_cats,0))="Да",FALSE),MAX($L$4:L22)+1,"")
I24: =IF(OR(G24="",H24=""),"",G24-H24) | L24: =IF(IFERROR(INDEX(lst_cat_wish,MATCH(D24,lst_cats,0))="Да",FALSE),MAX($L$4:L23)+1,"")
I25: =IF(OR(G25="",H25=""),"",G25-H25) | L25: =IF(IFERROR(INDEX(lst_cat_wish,MATCH(D25,lst_cats,0))="Да",FALSE),MAX($L$4:L24)+1,"")
I26: =IF(OR(G26="",H26=""),"",G26-H26) | L26: =IF(IFERROR(INDEX(lst_cat_wish,MATCH(D26,lst_cats,0))="Да",FALSE),MAX($L$4:L25)+1,"")
... I504: =IF(OR(G504="",H504=""),"",G504-H504) | L504: =IF(IFERROR(INDEX(lst_cat_wish,MATCH(D504,lst_cats,0))="Да",FALSE),MAX($L$4:L503)+1,"")

Sheet 💰 Доходы
A1: 💰 Доходы — сколько могу заработать и сколько получил
A2: Синяя колонка «ПЛАН» — сколько потенциально можно заработать (ЗП, проект, разовая услуга…), зелёная «ФАКТ» — сколько реально пришло. Статус «✅ Получено» зачёркивает строку.
E3: Σ видимых → | F3: =SUBTOTAL(9,F5:F304) | G3: =SUBTOTAL(9,G5:G304)
A4: 📆 Год | B4: 🗓 Месяц | C4: 💰 Источник | D4: 💼 Тип дохода | E4: ✏️ Описание | F4: 📝 ПЛАН, ₸ (потенциально) | G4: ✅ ФАКТ, ₸ (получено) | H4: ± Разница (факт − план) | I4: 🚦 Статус | J4: 💬 Комментарий
A5: 2026 | B5: Октябрь | C5: Основная работа | D5: 💼 Зарплата | E5: Оклад | F5: 500000 | G5: 500000 | H5: =IF(OR(F5="",G5=""),"",G5-F5) | I5: ✅ Получено
A6: 2026 | B6: Октябрь | C6: Консультация | D6: 🛠 Разовая услуга | E6: Настройка CRM | F6: 50000 | G6: 65000 | H6: =IF(OR(F6="",G6=""),"",G6-F6) | I6: ✅ Получено
A7: 2026 | B7: Ноябрь | C7: Основная работа | D7: 💼 Зарплата | E7: Оклад | F7: 500000 | H7: =IF(OR(F7="",G7=""),"",G7-F7) | I7: ⏳ Ожидается
A8: 2026 | B8: Ноябрь | C8: Фриланс-проект | D8: 🚀 Проект | E8: Сайт для клиента (50% аванс) | F8: 300000 | H8: =IF(OR(F8="",G8=""),"",G8-F8) | I8: ⏳ Ожидается
A9: 2026 | B9: Декабрь | C9: Основная работа | D9: 💼 Зарплата | E9: Оклад + годовая премия | F9: 750000 | H9: =IF(OR(F9="",G9=""),"",G9-F9) | I9: ⏳ Ожидается
A10: 2027 | B10: Январь | C10: Основная работа | D10: 💼 Зарплата | E10: Оклад (после индексации) | F10: 550000 | H10: =IF(OR(F10="",G10=""),"",G10-F10) | I10: ⏳ Ожидается
H11: =IF(OR(F11="",G11=""),"",G11-F11)
H12: =IF(OR(F12="",G12=""),"",G12-F12)
H13: =IF(OR(F13="",G13=""),"",G13-F13)
H14: =IF(OR(F14="",G14=""),"",G14-F14)
H15: =IF(OR(F15="",G15=""),"",G15-F15)
H16: =IF(OR(F16="",G16=""),"",G16-F16)
H17: =IF(OR(F17="",G17=""),"",G17-F17)
H18: =IF(OR(F18="",G18=""),"",G18-F18)
H19: =IF(OR(F19="",G19=""),"",G19-F19)
H20: =IF(OR(F20="",G20=""),"",G20-F20)
H21: =IF(OR(F21="",G21=""),"",G21-F21)
H22: =IF(OR(F22="",G22=""),"",G22-F22)
... H304: =IF(OR(F304="",G304=""),"",G304-F304)

Sheet 📅 По месяцам
A1: 📅 Сводка по месяцам: январь 2026 → декабрь 2030
A2: Считается автоматически из листов «Расходы» и «Доходы» — здесь ничего вводить не нужно. Текущий месяц подсвечен жёлтым. Отменённые траты в план не входят.
A4: 📆 Год | B4: 🗓 Месяц | C4: Подпись | D4: 💰 Доход ПЛАН | E4: 💰 Доход ФАКТ | F4: % дохода получено | G4: 💸 Расход ПЛАН | H4: 💸 Расход ФАКТ | I4: % бюджета потрачено | J4: ⚖️ Остаток ПЛАН | K4: ⚖️ Остаток ФАКТ | L4: 🏦 Накоплено ПЛАН (нараст.) | M4: 🏦 Накоплено ФАКТ (нараст.) | N4: 🏦 Отложено в «Накопление» (факт)
A5: 2026 | B5: Январь | C5: =LEFT(B5,3)&" "&RIGHT(A5,2) | D5: =SUMIFS(inc_plan,inc_year,A5,inc_month,B5,inc_status,"<>❌ Не получено") | E5: =SUMIFS(inc_fact,inc_year,A5,inc_month,B5) | F5: =IF(D5=0,"",E5/D5) | G5: =SUMIFS(exp_plan,exp_year,A5,exp_month,B5,exp_status,"<>❌ Отменено") | H5: =SUMIFS(exp_fact,exp_year,A5,exp_month,B5) | I5: =IF(G5=0,"",H5/G5) | J5: =D5-G5 | K5: =E5-H5 | L5: =J5 | M5: =K5 | N5: =SUMIFS(exp_fact,exp_year,A5,exp_month,B5,exp_cat,"🏦 Накопление")
A6: 2026 | B6: Февраль | C6: =LEFT(B6,3)&" "&RIGHT(A6,2) | D6: =SUMIFS(inc_plan,inc_year,A6,inc_month,B6,inc_status,"<>❌ Не получено") | E6: =SUMIFS(inc_fact,inc_year,A6,inc_month,B6) | F6: =IF(D6=0,"",E6/D6) | G6: =SUMIFS(exp_plan,exp_year,A6,exp_month,B6,exp_status,"<>❌ Отменено") | H6: =SUMIFS(exp_fact,exp_year,A6,exp_month,B6) | I6: =IF(G6=0,"",H6/G6) | J6: =D6-G6 | K6: =E6-H6 | L6: =L5+J6 | M6: =M5+K6 | N6: =SUMIFS(exp_fact,exp_year,A6,exp_month,B6,exp_cat,"🏦 Накопление")
A7: 2026 | B7: Март | C7: =LEFT(B7,3)&" "&RIGHT(A7,2) | D7: =SUMIFS(inc_plan,inc_year,A7,inc_month,B7,inc_status,"<>❌ Не получено") | E7: =SUMIFS(inc_fact,inc_year,A7,inc_month,B7) | F7: =IF(D7=0,"",E7/D7) | G7: =SUMIFS(exp_plan,exp_year,A7,exp_month,B7,exp_status,"<>❌ Отменено") | H7: =SUMIFS(exp_fact,exp_year,A7,exp_month,B7) | I7: =IF(G7=0,"",H7/G7) | J7: =D7-G7 | K7: =E7-H7 | L7: =L6+J7 | M7: =M6+K7 | N7: =SUMIFS(exp_fact,exp_year,A7,exp_month,B7,exp_cat,"🏦 Накопление")
A8: 2026 | B8: Апрель | C8: =LEFT(B8,3)&" "&RIGHT(A8,2) | D8: =SUMIFS(inc_plan,inc_year,A8,inc_month,B8,inc_status,"<>❌ Не получено") | E8: =SUMIFS(inc_fact,inc_year,A8,inc_month,B8) | F8: =IF(D8=0,"",E8/D8) | G8: =SUMIFS(exp_plan,exp_year,A8,exp_month,B8,exp_status,"<>❌ Отменено") | H8: =SUMIFS(exp_fact,exp_year,A8,exp_month,B8) | I8: =IF(G8=0,"",H8/G8) | J8: =D8-G8 | K8: =E8-H8 | L8: =L7+J8 | M8: =M7+K8 | N8: =SUMIFS(exp_fact,exp_year,A8,exp_month,B8,exp_cat,"🏦 Накопление")
A9: 2026 | B9: Май | C9: =LEFT(B9,3)&" "&RIGHT(A9,2) | D9: =SUMIFS(inc_plan,inc_year,A9,inc_month,B9,inc_status,"<>❌ Не получено") | E9: =SUMIFS(inc_fact,inc_year,A9,inc_month,B9) | F9: =IF(D9=0,"",E9/D9) | G9: =SUMIFS(exp_plan,exp_year,A9,exp_month,B9,exp_status,"<>❌ Отменено") | H9: =SUMIFS(exp_fact,exp_year,A9,exp_month,B9) | I9: =IF(G9=0,"",H9/G9) | J9: =D9-G9 | K9: =E9-H9 | L9: =L8+J9 | M9: =M8+K9 | N9: =SUMIFS(exp_fact,exp_year,A9,exp_month,B9,exp_cat,"🏦 Накопление")
A10: 2026 | B10: Июнь | C10: =LEFT(B10,3)&" "&RIGHT(A10,2) | D10: =SUMIFS(inc_plan,inc_year,A10,inc_month,B10,inc_status,"<>❌ Не получено") | E10: =SUMIFS(inc_fact,inc_year,A10,inc_month,B10) | F10: =IF(D10=0,"",E10/D10) | G10: =SUMIFS(exp_plan,exp_year,A10,exp_month,B10,exp_status,"<>❌ Отменено") | H10: =SUMIFS(exp_fact,exp_year,A10,exp_month,B10) | I10: =IF(G10=0,"",H10/G10) | J10: =D10-G10 | K10: =E10-H10 | L10: =L9+J10 | M10: =M9+K10 | N10: =SUMIFS(exp_fact,exp_year,A10,exp_month,B10,exp_cat,"🏦 Накопление")
A11: 2026 | B11: Июль | C11: =LEFT(B11,3)&" "&RIGHT(A11,2) | D11: =SUMIFS(inc_plan,inc_year,A11,inc_month,B11,inc_status,"<>❌ Не получено") | E11: =SUMIFS(inc_fact,inc_year,A11,inc_month,B11) | F11: =IF(D11=0,"",E11/D11) | G11: =SUMIFS(exp_plan,exp_year,A11,exp_month,B11,exp_status,"<>❌ Отменено") | H11: =SUMIFS(exp_fact,exp_year,A11,exp_month,B11) | I11: =IF(G11=0,"",H11/G11) | J11: =D11-G11 | K11: =E11-H11 | L11: =L10+J11 | M11: =M10+K11 | N11: =SUMIFS(exp_fact,exp_year,A11,exp_month,B11,exp_cat,"🏦 Накопление")
A12: 2026 | B12: Август | C12: =LEFT(B12,3)&" "&RIGHT(A12,2) | D12: =SUMIFS(inc_plan,inc_year,A12,inc_month,B12,inc_status,"<>❌ Не получено") | E12: =SUMIFS(inc_fact,inc_year,A12,inc_month,B12) | F12: =IF(D12=0,"",E12/D12) | G12: =SUMIFS(exp_plan,exp_year,A12,exp_month,B12,exp_status,"<>❌ Отменено") | H12: =SUMIFS(exp_fact,exp_year,A12,exp_month,B12) | I12: =IF(G12=0,"",H12/G12) | J12: =D12-G12 | K12: =E12-H12 | L12: =L11+J12 | M12: =M11+K12 | N12: =SUMIFS(exp_fact,exp_year,A12,exp_month,B12,exp_cat,"🏦 Накопление")
A13: 2026 | B13: Сентябрь | C13: =LEFT(B13,3)&" "&RIGHT(A13,2) | D13: =SUMIFS(inc_plan,inc_year,A13,inc_month,B13,inc_status,"<>❌ Не получено") | E13: =SUMIFS(inc_fact,inc_year,A13,inc_month,B13) | F13: =IF(D13=0,"",E13/D13) | G13: =SUMIFS(exp_plan,exp_year,A13,exp_month,B13,exp_status,"<>❌ Отменено") | H13: =SUMIFS(exp_fact,exp_year,A13,exp_month,B13) | I13: =IF(G13=0,"",H13/G13) | J13: =D13-G13 | K13: =E13-H13 | L13: =L12+J13 | M13: =M12+K13 | N13: =SUMIFS(exp_fact,exp_year,A13,exp_month,B13,exp_cat,"🏦 Накопление")
A14: 2026 | B14: Октябрь | C14: =LEFT(B14,3)&" "&RIGHT(A14,2) | D14: =SUMIFS(inc_plan,inc_year,A14,inc_month,B14,inc_status,"<>❌ Не получено") | E14: =SUMIFS(inc_fact,inc_year,A14,inc_month,B14) | F14: =IF(D14=0,"",E14/D14) | G14: =SUMIFS(exp_plan,exp_year,A14,exp_month,B14,exp_status,"<>❌ Отменено") | H14: =SUMIFS(exp_fact,exp_year,A14,exp_month,B14) | I14: =IF(G14=0,"",H14/G14) | J14: =D14-G14 | K14: =E14-H14 | L14: =L13+J14 | M14: =M13+K14 | N14: =SUMIFS(exp_fact,exp_year,A14,exp_month,B14,exp_cat,"🏦 Накопление")
A15: 2026 | B15: Ноябрь | C15: =LEFT(B15,3)&" "&RIGHT(A15,2) | D15: =SUMIFS(inc_plan,inc_year,A15,inc_month,B15,inc_status,"<>❌ Не получено") | E15: =SUMIFS(inc_fact,inc_year,A15,inc_month,B15) | F15: =IF(D15=0,"",E15/D15) | G15: =SUMIFS(exp_plan,exp_year,A15,exp_month,B15,exp_status,"<>❌ Отменено") | H15: =SUMIFS(exp_fact,exp_year,A15,exp_month,B15) | I15: =IF(G15=0,"",H15/G15) | J15: =D15-G15 | K15: =E15-H15 | L15: =L14+J15 | M15: =M14+K15 | N15: =SUMIFS(exp_fact,exp_year,A15,exp_month,B15,exp_cat,"🏦 Накопление")
A16: 2026 | B16: Декабрь | C16: =LEFT(B16,3)&" "&RIGHT(A16,2) | D16: =SUMIFS(inc_plan,inc_year,A16,inc_month,B16,inc_status,"<>❌ Не получено") | E16: =SUMIFS(inc_fact,inc_year,A16,inc_month,B16) | F16: =IF(D16=0,"",E16/D16) | G16: =SUMIFS(exp_plan,exp_year,A16,exp_month,B16,exp_status,"<>❌ Отменено") | H16: =SUMIFS(exp_fact,exp_year,A16,exp_month,B16) | I16: =IF(G16=0,"",H16/G16) | J16: =D16-G16 | K16: =E16-H16 | L16: =L15+J16 | M16: =M15+K16 | N16: =SUMIFS(exp_fact,exp_year,A16,exp_month,B16,exp_cat,"🏦 Накопление")
A17: 2027 | B17: Январь | C17: =LEFT(B17,3)&" "&RIGHT(A17,2) | D17: =SUMIFS(inc_plan,inc_year,A17,inc_month,B17,inc_status,"<>❌ Не получено") | E17: =SUMIFS(inc_fact,inc_year,A17,inc_month,B17) | F17: =IF(D17=0,"",E17/D17) | G17: =SUMIFS(exp_plan,exp_year,A17,exp_month,B17,exp_status,"<>❌ Отменено") | H17: =SUMIFS(exp_fact,exp_year,A17,exp_month,B17) | I17: =IF(G17=0,"",H17/G17) | J17: =D17-G17 | K17: =E17-H17 | L17: =L16+J17 | M17: =M16+K17 | N17: =SUMIFS(exp_fact,exp_year,A17,exp_month,B17,exp_cat,"🏦 Накопление")
... A64: 2030 | B64: Декабрь | C64: =LEFT(B64,3)&" "&RIGHT(A64,2) | D64: =SUMIFS(inc_plan,inc_year,A64,inc_month,B64,inc_status,"<>❌ Не получено") | E64: =SUMIFS(inc_fact,inc_year,A64,inc_month,B64) | F64: =IF(D64=0,"",E64/D64) | G64: =SUMIFS(exp_plan,exp_year,A64,exp_month,B64,exp_status,"<>❌ Отменено") | H64: =SUMIFS(exp_fact,exp_year,A64,exp_month,B64) | I64: =IF(G64=0,"",H64/G64) | J64: =D64-G64 | K64: =E64-H64 | L64: =L63+J64 | M64: =M63+K64 | N64: =SUMIFS(exp_fact,exp_year,A64,exp_month,B64,exp_cat,"🏦 Накопление")
A65: Σ ИТОГО | D65: =SUM(D5:D64) | E65: =SUM(E5:E64) | F65: =IF(D65=0,"",E65/D65) | G65: =SUM(G5:G64) | H65: =SUM(H5:H64) | I65: =IF(G65=0,"",H65/G65) | J65: =SUM(J5:J64) | K65: =SUM(K5:K64) | N65: =SUM(N5:N64)

Sheet 📊 По годам
A1: 📊 Сводка по годам 2026–2030
A2: Верхняя таблица — общий итог по годам, нижняя — расходы в разрезе категорий. Всё считается автоматически. Норма сбережений = остаток ÷ доход.
A4: 📆 Год | B4: 💰 Доход ПЛАН | C4: 💰 Доход ФАКТ | D4: % дохода получено | E4: 💸 Расход ПЛАН | F4: 💸 Расход ФАКТ | G4: % бюджета потрачено | H4: ⚖️ Остаток ПЛАН | I4: ⚖️ Остаток ФАКТ | J4: 💎 Норма сбере- жений ПЛАН | K4: 💎 Норма сбере- жений ФАКТ
A5: 2026 | B5: =SUMIFS(inc_plan,inc_year,A5,inc_status,"<>❌ Не получено") | C5: =SUMIFS(inc_fact,inc_year,A5) | D5: =IF(B5=0,"",C5/B5) | E5: =SUMIFS(exp_plan,exp_year,A5,exp_status,"<>❌ Отменено") | F5: =SUMIFS(exp_fact,exp_year,A5) | G5: =IF(E5=0,"",F5/E5) | H5: =B5-E5 | I5: =C5-F5 | J5: =IF(B5=0,"",H5/B5) | K5: =IF(C5=0,"",I5/C5)
A6: 2027 | B6: =SUMIFS(inc_plan,inc_year,A6,inc_status,"<>❌ Не получено") | C6: =SUMIFS(inc_fact,inc_year,A6) | D6: =IF(B6=0,"",C6/B6) | E6: =SUMIFS(exp_plan,exp_year,A6,exp_status,"<>❌ Отменено") | F6: =SUMIFS(exp_fact,exp_year,A6) | G6: =IF(E6=0,"",F6/E6) | H6: =B6-E6 | I6: =C6-F6 | J6: =IF(B6=0,"",H6/B6) | K6: =IF(C6=0,"",I6/C6)
A7: 2028 | B7: =SUMIFS(inc_plan,inc_year,A7,inc_status,"<>❌ Не получено") | C7: =SUMIFS(inc_fact,inc_year,A7) | D7: =IF(B7=0,"",C7/B7) | E7: =SUMIFS(exp_plan,exp_year,A7,exp_status,"<>❌ Отменено") | F7: =SUMIFS(exp_fact,exp_year,A7) | G7: =IF(E7=0,"",F7/E7) | H7: =B7-E7 | I7: =C7-F7 | J7: =IF(B7=0,"",H7/B7) | K7: =IF(C7=0,"",I7/C7)
A8: 2029 | B8: =SUMIFS(inc_plan,inc_year,A8,inc_status,"<>❌ Не получено") | C8: =SUMIFS(inc_fact,inc_year,A8) | D8: =IF(B8=0,"",C8/B8) | E8: =SUMIFS(exp_plan,exp_year,A8,exp_status,"<>❌ Отменено") | F8: =SUMIFS(exp_fact,exp_year,A8) | G8: =IF(E8=0,"",F8/E8) | H8: =B8-E8 | I8: =C8-F8 | J8: =IF(B8=0,"",H8/B8) | K8: =IF(C8=0,"",I8/C8)
A9: 2030 | B9: =SUMIFS(inc_plan,inc_year,A9,inc_status,"<>❌ Не получено") | C9: =SUMIFS(inc_fact,inc_year,A9) | D9: =IF(B9=0,"",C9/B9) | E9: =SUMIFS(exp_plan,exp_year,A9,exp_status,"<>❌ Отменено") | F9: =SUMIFS(exp_fact,exp_year,A9) | G9: =IF(E9=0,"",F9/E9) | H9: =B9-E9 | I9: =C9-F9 | J9: =IF(B9=0,"",H9/B9) | K9: =IF(C9=0,"",I9/C9)
A10: Σ 2026–2030 | B10: =SUM(B5:B9) | C10: =SUM(C5:C9) | D10: =IF(B10=0,"",C10/B10) | E10: =SUM(E5:E9) | F10: =SUM(F5:F9) | G10: =IF(E10=0,"",F10/E10) | H10: =SUM(H5:H9) | I10: =SUM(I5:I9) | J10: =IF(B10=0,"",H10/B10) | K10: =IF(C10=0,"",I10/C10)
A12: 🏷 Расходы по категориям и годам
A13: Категория | B13: 2026 | D13: 2027 | F13: 2028 | H13: 2029 | J13: 2030 | L13: Σ Итого
B14: 📝 План | C14: ✅ Факт | D14: 📝 План | E14: ✅ Факт | F14: 📝 План | G14: ✅ Факт | H14: 📝 План | I14: ✅ Факт | J14: 📝 План | K14: ✅ Факт | L14: 📝 План | M14: ✅ Факт
A15: =IF('📚 Справочник'!D5="","",'📚 Справочник'!D5) | B15: =IF($A15="","",SUMIFS(exp_plan,exp_cat,$A15,exp_year,2026,exp_status,"<>❌ Отменено")) | C15: =IF($A15="","",SUMIFS(exp_fact,exp_cat,$A15,exp_year,2026)) | D15: =IF($A15="","",SUMIFS(exp_plan,exp_cat,$A15,exp_year,2027,exp_status,"<>❌ Отменено")) | E15: =IF($A15="","",SUMIFS(exp_fact,exp_cat,$A15,exp_year,2027)) | F15: =IF($A15="","",SUMIFS(exp_plan,exp_cat,$A15,exp_year,2028,exp_status,"<>❌ Отменено")) | G15: =IF($A15="","",SUMIFS(exp_fact,exp_cat,$A15,exp_year,2028)) | H15: =IF($A15="","",SUMIFS(exp_plan,exp_cat,$A15,exp_year,2029,exp_status,"<>❌ Отменено")) | I15: =IF($A15="","",SUMIFS(exp_fact,exp_cat,$A15,exp_year,2029)) | J15: =IF($A15="","",SUMIFS(exp_plan,exp_cat,$A15,exp_year,2030,exp_status,"<>❌ Отменено")) | K15: =IF($A15="","",SUMIFS(exp_fact,exp_cat,$A15,exp_year,2030)) | L15: =IF($A15="","",SUM(B15,D15,F15,H15,J15)) | M15: =IF($A15="","",SUM(C15,E15,G15,I15,K15))
A16: =IF('📚 Справочник'!D6="","",'📚 Справочник'!D6) | B16: =IF($A16="","",SUMIFS(exp_plan,exp_cat,$A16,exp_year,2026,exp_status,"<>❌ Отменено")) | C16: =IF($A16="","",SUMIFS(exp_fact,exp_cat,$A16,exp_year,2026)) | D16: =IF($A16="","",SUMIFS(exp_plan,exp_cat,$A16,exp_year,2027,exp_status,"<>❌ Отменено")) | E16: =IF($A16="","",SUMIFS(exp_fact,exp_cat,$A16,exp_year,2027)) | F16: =IF($A16="","",SUMIFS(exp_plan,exp_cat,$A16,exp_year,2028,exp_status,"<>❌ Отменено")) | G16: =IF($A16="","",SUMIFS(exp_fact,exp_cat,$A16,exp_year,2028)) | H16: =IF($A16="","",SUMIFS(exp_plan,exp_cat,$A16,exp_year,2029,exp_status,"<>❌ Отменено")) | I16: =IF($A16="","",SUMIFS(exp_fact,exp_cat,$A16,exp_year,2029)) | J16: =IF($A16="","",SUMIFS(exp_plan,exp_cat,$A16,exp_year,2030,exp_status,"<>❌ Отменено")) | K16: =IF($A16="","",SUMIFS(exp_fact,exp_cat,$A16,exp_year,2030)) | L16: =IF($A16="","",SUM(B16,D16,F16,H16,J16)) | M16: =IF($A16="","",SUM(C16,E16,G16,I16,K16))
A17: =IF('📚 Справочник'!D7="","",'📚 Справочник'!D7) | B17: =IF($A17="","",SUMIFS(exp_plan,exp_cat,$A17,exp_year,2026,exp_status,"<>❌ Отменено")) | C17: =IF($A17="","",SUMIFS(exp_fact,exp_cat,$A17,exp_year,2026)) | D17: =IF($A17="","",SUMIFS(exp_plan,exp_cat,$A17,exp_year,2027,exp_status,"<>❌ Отменено")) | E17: =IF($A17="","",SUMIFS(exp_fact,exp_cat,$A17,exp_year,2027)) | F17: =IF($A17="","",SUMIFS(exp_plan,exp_cat,$A17,exp_year,2028,exp_status,"<>❌ Отменено")) | G17: =IF($A17="","",SUMIFS(exp_fact,exp_cat,$A17,exp_year,2028)) | H17: =IF($A17="","",SUMIFS(exp_plan,exp_cat,$A17,exp_year,2029,exp_status,"<>❌ Отменено")) | I17: =IF($A17="","",SUMIFS(exp_fact,exp_cat,$A17,exp_year,2029)) | J17: =IF($A17="","",SUMIFS(exp_plan,exp_cat,$A17,exp_year,2030,exp_status,"<>❌ Отменено")) | K17: =IF($A17="","",SUMIFS(exp_fact,exp_cat,$A17,exp_year,2030)) | L17: =IF($A17="","",SUM(B17,D17,F17,H17,J17)) | M17: =IF($A17="","",SUM(C17,E17,G17,I17,K17))
A18: =IF('📚 Справочник'!D8="","",'📚 Справочник'!D8) | B18: =IF($A18="","",SUMIFS(exp_plan,exp_cat,$A18,exp_year,2026,exp_status,"<>❌ Отменено")) | C18: =IF($A18="","",SUMIFS(exp_fact,exp_cat,$A18,exp_year,2026)) | D18: =IF($A18="","",SUMIFS(exp_plan,exp_cat,$A18,exp_year,2027,exp_status,"<>❌ Отменено")) | E18: =IF($A18="","",SUMIFS(exp_fact,exp_cat,$A18,exp_year,2027)) | F18: =IF($A18="","",SUMIFS(exp_plan,exp_cat,$A18,exp_year,2028,exp_status,"<>❌ Отменено")) | G18: =IF($A18="","",SUMIFS(exp_fact,exp_cat,$A18,exp_year,2028)) | H18: =IF($A18="","",SUMIFS(exp_plan,exp_cat,$A18,exp_year,2029,exp_status,"<>❌ Отменено")) | I18: =IF($A18="","",SUMIFS(exp_fact,exp_cat,$A18,exp_year,2029)) | J18: =IF($A18="","",SUMIFS(exp_plan,exp_cat,$A18,exp_year,2030,exp_status,"<>❌ Отменено")) | K18: =IF($A18="","",SUMIFS(exp_fact,exp_cat,$A18,exp_year,2030)) | L18: =IF($A18="","",SUM(B18,D18,F18,H18,J18)) | M18: =IF($A18="","",SUM(C18,E18,G18,I18,K18))
A19: =IF('📚 Справочник'!D9="","",'📚 Справочник'!D9) | B19: =IF($A19="","",SUMIFS(exp_plan,exp_cat,$A19,exp_year,2026,exp_status,"<>❌ Отменено")) | C19: =IF($A19="","",SUMIFS(exp_fact,exp_cat,$A19,exp_year,2026)) | D19: =IF($A19="","",SUMIFS(exp_plan,exp_cat,$A19,exp_year,2027,exp_status,"<>❌ Отменено")) | E19: =IF($A19="","",SUMIFS(exp_fact,exp_cat,$A19,exp_year,2027)) | F19: =IF($A19="","",SUMIFS(exp_plan,exp_cat,$A19,exp_year,2028,exp_status,"<>❌ Отменено")) | G19: =IF($A19="","",SUMIFS(exp_fact,exp_cat,$A19,exp_year,2028)) | H19: =IF($A19="","",SUMIFS(exp_plan,exp_cat,$A19,exp_year,2029,exp_status,"<>❌ Отменено")) | I19: =IF($A19="","",SUMIFS(exp_fact,exp_cat,$A19,exp_year,2029)) | J19: =IF($A19="","",SUMIFS(exp_plan,exp_cat,$A19,exp_year,2030,exp_status,"<>❌ Отменено")) | K19: =IF($A19="","",SUMIFS(exp_fact,exp_cat,$A19,exp_year,2030)) | L19: =IF($A19="","",SUM(B19,D19,F19,H19,J19)) | M19: =IF($A19="","",SUM(C19,E19,G19,I19,K19))
A20: =IF('📚 Справочник'!D10="","",'📚 Справочник'!D10) | B20: =IF($A20="","",SUMIFS(exp_plan,exp_cat,$A20,exp_year,2026,exp_status,"<>❌ Отменено")) | C20: =IF($A20="","",SUMIFS(exp_fact,exp_cat,$A20,exp_year,2026)) | D20: =IF($A20="","",SUMIFS(exp_plan,exp_cat,$A20,exp_year,2027,exp_status,"<>❌ Отменено")) | E20: =IF($A20="","",SUMIFS(exp_fact,exp_cat,$A20,exp_year,2027)) | F20: =IF($A20="","",SUMIFS(exp_plan,exp_cat,$A20,exp_year,2028,exp_status,"<>❌ Отменено")) | G20: =IF($A20="","",SUMIFS(exp_fact,exp_cat,$A20,exp_year,2028)) | H20: =IF($A20="","",SUMIFS(exp_plan,exp_cat,$A20,exp_year,2029,exp_status,"<>❌ Отменено")) | I20: =IF($A20="","",SUMIFS(exp_fact,exp_cat,$A20,exp_year,2029)) | J20: =IF($A20="","",SUMIFS(exp_plan,exp_cat,$A20,exp_year,2030,exp_status,"<>❌ Отменено")) | K20: =IF($A20="","",SUMIFS(exp_fact,exp_cat,$A20,exp_year,2030)) | L20: =IF($A20="","",SUM(B20,D20,F20,H20,J20)) | M20: =IF($A20="","",SUM(C20,E20,G20,I20,K20))
A21: =IF('📚 Справочник'!D11="","",'📚 Справочник'!D11) | B21: =IF($A21="","",SUMIFS(exp_plan,exp_cat,$A21,exp_year,2026,exp_status,"<>❌ Отменено")) | C21: =IF($A21="","",SUMIFS(exp_fact,exp_cat,$A21,exp_year,2026)) | D21: =IF($A21="","",SUMIFS(exp_plan,exp_cat,$A21,exp_year,2027,exp_status,"<>❌ Отменено")) | E21: =IF($A21="","",SUMIFS(exp_fact,exp_cat,$A21,exp_year,2027)) | F21: =IF($A21="","",SUMIFS(exp_plan,exp_cat,$A21,exp_year,2028,exp_status,"<>❌ Отменено")) | G21: =IF($A21="","",SUMIFS(exp_fact,exp_cat,$A21,exp_year,2028)) | H21: =IF($A21="","",SUMIFS(exp_plan,exp_cat,$A21,exp_year,2029,exp_status,"<>❌ Отменено")) | I21: =IF($A21="","",SUMIFS(exp_fact,exp_cat,$A21,exp_year,2029)) | J21: =IF($A21="","",SUMIFS(exp_plan,exp_cat,$A21,exp_year,2030,exp_status,"<>❌ Отменено")) | K21: =IF($A21="","",SUMIFS(exp_fact,exp_cat,$A21,exp_year,2030)) | L21: =IF($A21="","",SUM(B21,D21,F21,H21,J21)) | M21: =IF($A21="","",SUM(C21,E21,G21,I21,K21))
A22: =IF('📚 Справочник'!D12="","",'📚 Справочник'!D12) | B22: =IF($A22="","",SUMIFS(exp_plan,exp_cat,$A22,exp_year,2026,exp_status,"<>❌ Отменено")) | C22: =IF($A22="","",SUMIFS(exp_fact,exp_cat,$A22,exp_year,2026)) | D22: =IF($A22="","",SUMIFS(exp_plan,exp_cat,$A22,exp_year,2027,exp_status,"<>❌ Отменено")) | E22: =IF($A22="","",SUMIFS(exp_fact,exp_cat,$A22,exp_year,2027)) | F22: =IF($A22="","",SUMIFS(exp_plan,exp_cat,$A22,exp_year,2028,exp_status,"<>❌ Отменено")) | G22: =IF($A22="","",SUMIFS(exp_fact,exp_cat,$A22,exp_year,2028)) | H22: =IF($A22="","",SUMIFS(exp_plan,exp_cat,$A22,exp_year,2029,exp_status,"<>❌ Отменено")) | I22: =IF($A22="","",SUMIFS(exp_fact,exp_cat,$A22,exp_year,2029)) | J22: =IF($A22="","",SUMIFS(exp_plan,exp_cat,$A22,exp_year,2030,exp_status,"<>❌ Отменено")) | K22: =IF($A22="","",SUMIFS(exp_fact,exp_cat,$A22,exp_year,2030)) | L22: =IF($A22="","",SUM(B22,D22,F22,H22,J22)) | M22: =IF($A22="","",SUM(C22,E22,G22,I22,K22))
A23: =IF('📚 Справочник'!D13="","",'📚 Справочник'!D13) | B23: =IF($A23="","",SUMIFS(exp_plan,exp_cat,$A23,exp_year,2026,exp_status,"<>❌ Отменено")) | C23: =IF($A23="","",SUMIFS(exp_fact,exp_cat,$A23,exp_year,2026)) | D23: =IF($A23="","",SUMIFS(exp_plan,exp_cat,$A23,exp_year,2027,exp_status,"<>❌ Отменено")) | E23: =IF($A23="","",SUMIFS(exp_fact,exp_cat,$A23,exp_year,2027)) | F23: =IF($A23="","",SUMIFS(exp_plan,exp_cat,$A23,exp_year,2028,exp_status,"<>❌ Отменено")) | G23: =IF($A23="","",SUMIFS(exp_fact,exp_cat,$A23,exp_year,2028)) | H23: =IF($A23="","",SUMIFS(exp_plan,exp_cat,$A23,exp_year,2029,exp_status,"<>❌ Отменено")) | I23: =IF($A23="","",SUMIFS(exp_fact,exp_cat,$A23,exp_year,2029)) | J23: =IF($A23="","",SUMIFS(exp_plan,exp_cat,$A23,exp_year,2030,exp_status,"<>❌ Отменено")) | K23: =IF($A23="","",SUMIFS(exp_fact,exp_cat,$A23,exp_year,2030)) | L23: =IF($A23="","",SUM(B23,D23,F23,H23,J23)) | M23: =IF($A23="","",SUM(C23,E23,G23,I23,K23))
A24: =IF('📚 Справочник'!D14="","",'📚 Справочник'!D14) | B24: =IF($A24="","",SUMIFS(exp_plan,exp_cat,$A24,exp_year,2026,exp_status,"<>❌ Отменено")) | C24: =IF($A24="","",SUMIFS(exp_fact,exp_cat,$A24,exp_year,2026)) | D24: =IF($A24="","",SUMIFS(exp_plan,exp_cat,$A24,exp_year,2027,exp_status,"<>❌ Отменено")) | E24: =IF($A24="","",SUMIFS(exp_fact,exp_cat,$A24,exp_year,2027)) | F24: =IF($A24="","",SUMIFS(exp_plan,exp_cat,$A24,exp_year,2028,exp_status,"<>❌ Отменено")) | G24: =IF($A24="","",SUMIFS(exp_fact,exp_cat,$A24,exp_year,2028)) | H24: =IF($A24="","",SUMIFS(exp_plan,exp_cat,$A24,exp_year,2029,exp_status,"<>❌ Отменено")) | I24: =IF($A24="","",SUMIFS(exp_fact,exp_cat,$A24,exp_year,2029)) | J24: =IF($A24="","",SUMIFS(exp_plan,exp_cat,$A24,exp_year,2030,exp_status,"<>❌ Отменено")) | K24: =IF($A24="","",SUMIFS(exp_fact,exp_cat,$A24,exp_year,2030)) | L24: =IF($A24="","",SUM(B24,D24,F24,H24,J24)) | M24: =IF($A24="","",SUM(C24,E24,G24,I24,K24))
A25: =IF('📚 Справочник'!D15="","",'📚 Справочник'!D15) | B25: =IF($A25="","",SUMIFS(exp_plan,exp_cat,$A25,exp_year,2026,exp_status,"<>❌ Отменено")) | C25: =IF($A25="","",SUMIFS(exp_fact,exp_cat,$A25,exp_year,2026)) | D25: =IF($A25="","",SUMIFS(exp_plan,exp_cat,$A25,exp_year,2027,exp_status,"<>❌ Отменено")) | E25: =IF($A25="","",SUMIFS(exp_fact,exp_cat,$A25,exp_year,2027)) | F25: =IF($A25="","",SUMIFS(exp_plan,exp_cat,$A25,exp_year,2028,exp_status,"<>❌ Отменено")) | G25: =IF($A25="","",SUMIFS(exp_fact,exp_cat,$A25,exp_year,2028)) | H25: =IF($A25="","",SUMIFS(exp_plan,exp_cat,$A25,exp_year,2029,exp_status,"<>❌ Отменено")) | I25: =IF($A25="","",SUMIFS(exp_fact,exp_cat,$A25,exp_year,2029)) | J25: =IF($A25="","",SUMIFS(exp_plan,exp_cat,$A25,exp_year,2030,exp_status,"<>❌ Отменено")) | K25: =IF($A25="","",SUMIFS(exp_fact,exp_cat,$A25,exp_year,2030)) | L25: =IF($A25="","",SUM(B25,D25,F25,H25,J25)) | M25: =IF($A25="","",SUM(C25,E25,G25,I25,K25))
A26: =IF('📚 Справочник'!D16="","",'📚 Справочник'!D16) | B26: =IF($A26="","",SUMIFS(exp_plan,exp_cat,$A26,exp_year,2026,exp_status,"<>❌ Отменено")) | C26: =IF($A26="","",SUMIFS(exp_fact,exp_cat,$A26,exp_year,2026)) | D26: =IF($A26="","",SUMIFS(exp_plan,exp_cat,$A26,exp_year,2027,exp_status,"<>❌ Отменено")) | E26: =IF($A26="","",SUMIFS(exp_fact,exp_cat,$A26,exp_year,2027)) | F26: =IF($A26="","",SUMIFS(exp_plan,exp_cat,$A26,exp_year,2028,exp_status,"<>❌ Отменено")) | G26: =IF($A26="","",SUMIFS(exp_fact,exp_cat,$A26,exp_year,2028)) | H26: =IF($A26="","",SUMIFS(exp_plan,exp_cat,$A26,exp_year,2029,exp_status,"<>❌ Отменено")) | I26: =IF($A26="","",SUMIFS(exp_fact,exp_cat,$A26,exp_year,2029)) | J26: =IF($A26="","",SUMIFS(exp_plan,exp_cat,$A26,exp_year,2030,exp_status,"<>❌ Отменено")) | K26: =IF($A26="","",SUMIFS(exp_fact,exp_cat,$A26,exp_year,2030)) | L26: =IF($A26="","",SUM(B26,D26,F26,H26,J26)) | M26: =IF($A26="","",SUM(C26,E26,G26,I26,K26))
... A29: =IF('📚 Справочник'!D19="","",'📚 Справочник'!D19) | B29: =IF($A29="","",SUMIFS(exp_plan,exp_cat,$A29,exp_year,2026,exp_status,"<>❌ Отменено")) | C29: =IF($A29="","",SUMIFS(exp_fact,exp_cat,$A29,exp_year,2026)) | D29: =IF($A29="","",SUMIFS(exp_plan,exp_cat,$A29,exp_year,2027,exp_status,"<>❌ Отменено")) | E29: =IF($A29="","",SUMIFS(exp_fact,exp_cat,$A29,exp_year,2027)) | F29: =IF($A29="","",SUMIFS(exp_plan,exp_cat,$A29,exp_year,2028,exp_status,"<>❌ Отменено")) | G29: =IF($A29="","",SUMIFS(exp_fact,exp_cat,$A29,exp_year,2028)) | H29: =IF($A29="","",SUMIFS(exp_plan,exp_cat,$A29,exp_year,2029,exp_status,"<>❌ Отменено")) | I29: =IF($A29="","",SUMIFS(exp_fact,exp_cat,$A29,exp_year,2029)) | J29: =IF($A29="","",SUMIFS(exp_plan,exp_cat,$A29,exp_year,2030,exp_status,"<>❌ Отменено")) | K29: =IF($A29="","",SUMIFS(exp_fact,exp_cat,$A29,exp_year,2030)) | L29: =IF($A29="","",SUM(B29,D29,F29,H29,J29)) | M29: =IF($A29="","",SUM(C29,E29,G29,I29,K29))
A30: Σ ИТОГО | B30: =SUM(B15:B29) | C30: =SUM(C15:C29) | D30: =SUM(D15:D29) | E30: =SUM(E15:E29) | F30: =SUM(F15:F29) | G30: =SUM(G15:G29) | H30: =SUM(H15:H29) | I30: =SUM(I15:I29) | ... M30: =SUM(M15:M29)

Sheet ✨ Хотелки
A1: ✨ Список хотелок, желаний и мечт
A2: Собирается АВТОМАТИЧЕСКИ из листа «💸 Расходы» по категориям с отметкой «Да» в справочнике. Чтобы вычеркнуть хотелку — поставьте ей статус «✅ Выполнено» в листе «Расходы».
B3: Всего хотелок | C3: ✅ Исполнено | D3: 🎯 Прогресс | E3: 💰 Ещё нужно, ₸
B4: =COUNT(exp_wishno) | C4: =COUNTIFS(exp_wishno,">0",exp_status,"✅ Выполнено") | D4: =IF(B4=0,"",C4/B4) | E4: =SUMPRODUCT((exp_wishno<>"")*(exp_status<>"✅ Выполнено")*(exp_status<>"❌ Отменено"),exp_plan)
A6: № | B6: ✨ Хотелка | C6: 🏷 Категория | D6: 🎯 Приоритет | E6: 📆 Год | F6: 🗓 Месяц | G6: 📝 ПЛАН, ₸ | H6: ✅ ФАКТ, ₸ | I6: 🚦 Статус
A7: =IF(ISNA(MATCH(1,exp_wishno,0)),"",1) | B7: =IF($A7="","",IF(INDEX(exp_desc,MATCH(1,exp_wishno,0))="","",INDEX(exp_desc,MATCH(1,exp_wishno,0)))) | C7: =IF($A7="","",IF(INDEX(exp_cat,MATCH(1,exp_wishno,0))="","",INDEX(exp_cat,MATCH(1,exp_wishno,0)))) | D7: =IF($A7="","",IF(INDEX(exp_prio,MATCH(1,exp_wishno,0))="","",INDEX(exp_prio,MATCH(1,exp_wishno,0)))) | E7: =IF($A7="","",IF(INDEX(exp_year,MATCH(1,exp_wishno,0))="","",INDEX(exp_year,MATCH(1,exp_wishno,0)))) | F7: =IF($A7="","",IF(INDEX(exp_month,MATCH(1,exp_wishno,0))="","",INDEX(exp_month,MATCH(1,exp_wishno,0)))) | G7: =IF($A7="","",IF(INDEX(exp_plan,MATCH(1,exp_wishno,0))="","",INDEX(exp_plan,MATCH(1,exp_wishno,0)))) | H7: =IF($A7="","",IF(INDEX(exp_fact,MATCH(1,exp_wishno,0))="","",INDEX(exp_fact,MATCH(1,exp_wishno,0)))) | I7: =IF($A7="","",IF(INDEX(exp_status,MATCH(1,exp_wishno,0))="","",INDEX(exp_status,MATCH(1,exp_wishno,0))))
A8: =IF(ISNA(MATCH(2,exp_wishno,0)),"",2) | B8: =IF($A8="","",IF(INDEX(exp_desc,MATCH(2,exp_wishno,0))="","",INDEX(exp_desc,MATCH(2,exp_wishno,0)))) | C8: =IF($A8="","",IF(INDEX(exp_cat,MATCH(2,exp_wishno,0))="","",INDEX(exp_cat,MATCH(2,exp_wishno,0)))) | D8: =IF($A8="","",IF(INDEX(exp_prio,MATCH(2,exp_wishno,0))="","",INDEX(exp_prio,MATCH(2,exp_wishno,0)))) | E8: =IF($A8="","",IF(INDEX(exp_year,MATCH(2,exp_wishno,0))="","",INDEX(exp_year,MATCH(2,exp_wishno,0)))) | F8: =IF($A8="","",IF(INDEX(exp_month,MATCH(2,exp_wishno,0))="","",INDEX(exp_month,MATCH(2,exp_wishno,0)))) | G8: =IF($A8="","",IF(INDEX(exp_plan,MATCH(2,exp_wishno,0))="","",INDEX(exp_plan,MATCH(2,exp_wishno,0)))) | H8: =IF($A8="","",IF(INDEX(exp_fact,MATCH(2,exp_wishno,0))="","",INDEX(exp_fact,MATCH(2,exp_wishno,0)))) | I8: =IF($A8="","",IF(INDEX(exp_status,MATCH(2,exp_wishno,0))="","",INDEX(exp_status,MATCH(2,exp_wishno,0))))
A9: =IF(ISNA(MATCH(3,exp_wishno,0)),"",3) | B9: =IF($A9="","",IF(INDEX(exp_desc,MATCH(3,exp_wishno,0))="","",INDEX(exp_desc,MATCH(3,exp_wishno,0)))) | C9: =IF($A9="","",IF(INDEX(exp_cat,MATCH(3,exp_wishno,0))="","",INDEX(exp_cat,MATCH(3,exp_wishno,0)))) | D9: =IF($A9="","",IF(INDEX(exp_prio,MATCH(3,exp_wishno,0))="","",INDEX(exp_prio,MATCH(3,exp_wishno,0)))) | E9: =IF($A9="","",IF(INDEX(exp_year,MATCH(3,exp_wishno,0))="","",INDEX(exp_year,MATCH(3,exp_wishno,0)))) | F9: =IF($A9="","",IF(INDEX(exp_month,MATCH(3,exp_wishno,0))="","",INDEX(exp_month,MATCH(3,exp_wishno,0)))) | G9: =IF($A9="","",IF(INDEX(exp_plan,MATCH(3,exp_wishno,0))="","",INDEX(exp_plan,MATCH(3,exp_wishno,0)))) | H9: =IF($A9="","",IF(INDEX(exp_fact,MATCH(3,exp_wishno,0))="","",INDEX(exp_fact,MATCH(3,exp_wishno,0)))) | I9: =IF($A9="","",IF(INDEX(exp_status,MATCH(3,exp_wishno,0))="","",INDEX(exp_status,MATCH(3,exp_wishno,0))))
A10: =IF(ISNA(MATCH(4,exp_wishno,0)),"",4) | B10: =IF($A10="","",IF(INDEX(exp_desc,MATCH(4,exp_wishno,0))="","",INDEX(exp_desc,MATCH(4,exp_wishno,0)))) | C10: =IF($A10="","",IF(INDEX(exp_cat,MATCH(4,exp_wishno,0))="","",INDEX(exp_cat,MATCH(4,exp_wishno,0)))) | D10: =IF($A10="","",IF(INDEX(exp_prio,MATCH(4,exp_wishno,0))="","",INDEX(exp_prio,MATCH(4,exp_wishno,0)))) | E10: =IF($A10="","",IF(INDEX(exp_year,MATCH(4,exp_wishno,0))="","",INDEX(exp_year,MATCH(4,exp_wishno,0)))) | F10: =IF($A10="","",IF(INDEX(exp_month,MATCH(4,exp_wishno,0))="","",INDEX(exp_month,MATCH(4,exp_wishno,0)))) | G10: =IF($A10="","",IF(INDEX(exp_plan,MATCH(4,exp_wishno,0))="","",INDEX(exp_plan,MATCH(4,exp_wishno,0)))) | H10: =IF($A10="","",IF(INDEX(exp_fact,MATCH(4,exp_wishno,0))="","",INDEX(exp_fact,MATCH(4,exp_wishno,0)))) | I10: =IF($A10="","",IF(INDEX(exp_status,MATCH(4,exp_wishno,0))="","",INDEX(exp_status,MATCH(4,exp_wishno,0))))
A11: =IF(ISNA(MATCH(5,exp_wishno,0)),"",5) | B11: =IF($A11="","",IF(INDEX(exp_desc,MATCH(5,exp_wishno,0))="","",INDEX(exp_desc,MATCH(5,exp_wishno,0)))) | C11: =IF($A11="","",IF(INDEX(exp_cat,MATCH(5,exp_wishno,0))="","",INDEX(exp_cat,MATCH(5,exp_wishno,0)))) | D11: =IF($A11="","",IF(INDEX(exp_prio,MATCH(5,exp_wishno,0))="","",INDEX(exp_prio,MATCH(5,exp_wishno,0)))) | E11: =IF($A11="","",IF(INDEX(exp_year,MATCH(5,exp_wishno,0))="","",INDEX(exp_year,MATCH(5,exp_wishno,0)))) | F11: =IF($A11="","",IF(INDEX(exp_month,MATCH(5,exp_wishno,0))="","",INDEX(exp_month,MATCH(5,exp_wishno,0)))) | G11: =IF($A11="","",IF(INDEX(exp_plan,MATCH(5,exp_wishno,0))="","",INDEX(exp_plan,MATCH(5,exp_wishno,0)))) | H11: =IF($A11="","",IF(INDEX(exp_fact,MATCH(5,exp_wishno,0))="","",INDEX(exp_fact,MATCH(5,exp_wishno,0)))) | I11: =IF($A11="","",IF(INDEX(exp_status,MATCH(5,exp_wishno,0))="","",INDEX(exp_status,MATCH(5,exp_wishno,0))))
A12: =IF(ISNA(MATCH(6,exp_wishno,0)),"",6) | B12: =IF($A12="","",IF(INDEX(exp_desc,MATCH(6,exp_wishno,0))="","",INDEX(exp_desc,MATCH(6,exp_wishno,0)))) | C12: =IF($A12="","",IF(INDEX(exp_cat,MATCH(6,exp_wishno,0))="","",INDEX(exp_cat,MATCH(6,exp_wishno,0)))) | D12: =IF($A12="","",IF(INDEX(exp_prio,MATCH(6,exp_wishno,0))="","",INDEX(exp_prio,MATCH(6,exp_wishno,0)))) | E12: =IF($A12="","",IF(INDEX(exp_year,MATCH(6,exp_wishno,0))="","",INDEX(exp_year,MATCH(6,exp_wishno,0)))) | F12: =IF($A12="","",IF(INDEX(exp_month,MATCH(6,exp_wishno,0))="","",INDEX(exp_month,MATCH(6,exp_wishno,0)))) | G12: =IF($A12="","",IF(INDEX(exp_plan,MATCH(6,exp_wishno,0))="","",INDEX(exp_plan,MATCH(6,exp_wishno,0)))) | H12: =IF($A12="","",IF(INDEX(exp_fact,MATCH(6,exp_wishno,0))="","",INDEX(exp_fact,MATCH(6,exp_wishno,0)))) | I12: =IF($A12="","",IF(INDEX(exp_status,MATCH(6,exp_wishno,0))="","",INDEX(exp_status,MATCH(6,exp_wishno,0))))
A13: =IF(ISNA(MATCH(7,exp_wishno,0)),"",7) | B13: =IF($A13="","",IF(INDEX(exp_desc,MATCH(7,exp_wishno,0))="","",INDEX(exp_desc,MATCH(7,exp_wishno,0)))) | C13: =IF($A13="","",IF(INDEX(exp_cat,MATCH(7,exp_wishno,0))="","",INDEX(exp_cat,MATCH(7,exp_wishno,0)))) | D13: =IF($A13="","",IF(INDEX(exp_prio,MATCH(7,exp_wishno,0))="","",INDEX(exp_prio,MATCH(7,exp_wishno,0)))) | E13: =IF($A13="","",IF(INDEX(exp_year,MATCH(7,exp_wishno,0))="","",INDEX(exp_year,MATCH(7,exp_wishno,0)))) | F13: =IF($A13="","",IF(INDEX(exp_month,MATCH(7,exp_wishno,0))="","",INDEX(exp_month,MATCH(7,exp_wishno,0)))) | G13: =IF($A13="","",IF(INDEX(exp_plan,MATCH(7,exp_wishno,0))="","",INDEX(exp_plan,MATCH(7,exp_wishno,0)))) | H13: =IF($A13="","",IF(INDEX(exp_fact,MATCH(7,exp_wishno,0))="","",INDEX(exp_fact,MATCH(7,exp_wishno,0)))) | I13: =IF($A13="","",IF(INDEX(exp_status,MATCH(7,exp_wishno,0))="","",INDEX(exp_status,MATCH(7,exp_wishno,0))))
A14: =IF(ISNA(MATCH(8,exp_wishno,0)),"",8) | B14: =IF($A14="","",IF(INDEX(exp_desc,MATCH(8,exp_wishno,0))="","",INDEX(exp_desc,MATCH(8,exp_wishno,0)))) | C14: =IF($A14="","",IF(INDEX(exp_cat,MATCH(8,exp_wishno,0))="","",INDEX(exp_cat,MATCH(8,exp_wishno,0)))) | D14: =IF($A14="","",IF(INDEX(exp_prio,MATCH(8,exp_wishno,0))="","",INDEX(exp_prio,MATCH(8,exp_wishno,0)))) | E14: =IF($A14="","",IF(INDEX(exp_year,MATCH(8,exp_wishno,0))="","",INDEX(exp_year,MATCH(8,exp_wishno,0)))) | F14: =IF($A14="","",IF(INDEX(exp_month,MATCH(8,exp_wishno,0))="","",INDEX(exp_month,MATCH(8,exp_wishno,0)))) | G14: =IF($A14="","",IF(INDEX(exp_plan,MATCH(8,exp_wishno,0))="","",INDEX(exp_plan,MATCH(8,exp_wishno,0)))) | H14: =IF($A14="","",IF(INDEX(exp_fact,MATCH(8,exp_wishno,0))="","",INDEX(exp_fact,MATCH(8,exp_wishno,0)))) | I14: =IF($A14="","",IF(INDEX(exp_status,MATCH(8,exp_wishno,0))="","",INDEX(exp_status,MATCH(8,exp_wishno,0))))
A15: =IF(ISNA(MATCH(9,exp_wishno,0)),"",9) | B15: =IF($A15="","",IF(INDEX(exp_desc,MATCH(9,exp_wishno,0))="","",INDEX(exp_desc,MATCH(9,exp_wishno,0)))) | C15: =IF($A15="","",IF(INDEX(exp_cat,MATCH(9,exp_wishno,0))="","",INDEX(exp_cat,MATCH(9,exp_wishno,0)))) | D15: =IF($A15="","",IF(INDEX(exp_prio,MATCH(9,exp_wishno,0))="","",INDEX(exp_prio,MATCH(9,exp_wishno,0)))) | E15: =IF($A15="","",IF(INDEX(exp_year,MATCH(9,exp_wishno,0))="","",INDEX(exp_year,MATCH(9,exp_wishno,0)))) | F15: =IF($A15="","",IF(INDEX(exp_month,MATCH(9,exp_wishno,0))="","",INDEX(exp_month,MATCH(9,exp_wishno,0)))) | G15: =IF($A15="","",IF(INDEX(exp_plan,MATCH(9,exp_wishno,0))="","",INDEX(exp_plan,MATCH(9,exp_wishno,0)))) | H15: =IF($A15="","",IF(INDEX(exp_fact,MATCH(9,exp_wishno,0))="","",INDEX(exp_fact,MATCH(9,exp_wishno,0)))) | I15: =IF($A15="","",IF(INDEX(exp_status,MATCH(9,exp_wishno,0))="","",INDEX(exp_status,MATCH(9,exp_wishno,0))))
A16: =IF(ISNA(MATCH(10,exp_wishno,0)),"",10) | B16: =IF($A16="","",IF(INDEX(exp_desc,MATCH(10,exp_wishno,0))="","",INDEX(exp_desc,MATCH(10,exp_wishno,0)))) | C16: =IF($A16="","",IF(INDEX(exp_cat,MATCH(10,exp_wishno,0))="","",INDEX(exp_cat,MATCH(10,exp_wishno,0)))) | D16: =IF($A16="","",IF(INDEX(exp_prio,MATCH(10,exp_wishno,0))="","",INDEX(exp_prio,MATCH(10,exp_wishno,0)))) | E16: =IF($A16="","",IF(INDEX(exp_year,MATCH(10,exp_wishno,0))="","",INDEX(exp_year,MATCH(10,exp_wishno,0)))) | F16: =IF($A16="","",IF(INDEX(exp_month,MATCH(10,exp_wishno,0))="","",INDEX(exp_month,MATCH(10,exp_wishno,0)))) | G16: =IF($A16="","",IF(INDEX(exp_plan,MATCH(10,exp_wishno,0))="","",INDEX(exp_plan,MATCH(10,exp_wishno,0)))) | H16: =IF($A16="","",IF(INDEX(exp_fact,MATCH(10,exp_wishno,0))="","",INDEX(exp_fact,MATCH(10,exp_wishno,0)))) | I16: =IF($A16="","",IF(INDEX(exp_status,MATCH(10,exp_wishno,0))="","",INDEX(exp_status,MATCH(10,exp_wishno,0))))
A17: =IF(ISNA(MATCH(11,exp_wishno,0)),"",11) | B17: =IF($A17="","",IF(INDEX(exp_desc,MATCH(11,exp_wishno,0))="","",INDEX(exp_desc,MATCH(11,exp_wishno,0)))) | C17: =IF($A17="","",IF(INDEX(exp_cat,MATCH(11,exp_wishno,0))="","",INDEX(exp_cat,MATCH(11,exp_wishno,0)))) | D17: =IF($A17="","",IF(INDEX(exp_prio,MATCH(11,exp_wishno,0))="","",INDEX(exp_prio,MATCH(11,exp_wishno,0)))) | E17: =IF($A17="","",IF(INDEX(exp_year,MATCH(11,exp_wishno,0))="","",INDEX(exp_year,MATCH(11,exp_wishno,0)))) | F17: =IF($A17="","",IF(INDEX(exp_month,MATCH(11,exp_wishno,0))="","",INDEX(exp_month,MATCH(11,exp_wishno,0)))) | G17: =IF($A17="","",IF(INDEX(exp_plan,MATCH(11,exp_wishno,0))="","",INDEX(exp_plan,MATCH(11,exp_wishno,0)))) | H17: =IF($A17="","",IF(INDEX(exp_fact,MATCH(11,exp_wishno,0))="","",INDEX(exp_fact,MATCH(11,exp_wishno,0)))) | I17: =IF($A17="","",IF(INDEX(exp_status,MATCH(11,exp_wishno,0))="","",INDEX(exp_status,MATCH(11,exp_wishno,0))))
A18: =IF(ISNA(MATCH(12,exp_wishno,0)),"",12) | B18: =IF($A18="","",IF(INDEX(exp_desc,MATCH(12,exp_wishno,0))="","",INDEX(exp_desc,MATCH(12,exp_wishno,0)))) | C18: =IF($A18="","",IF(INDEX(exp_cat,MATCH(12,exp_wishno,0))="","",INDEX(exp_cat,MATCH(12,exp_wishno,0)))) | D18: =IF($A18="","",IF(INDEX(exp_prio,MATCH(12,exp_wishno,0))="","",INDEX(exp_prio,MATCH(12,exp_wishno,0)))) | E18: =IF($A18="","",IF(INDEX(exp_year,MATCH(12,exp_wishno,0))="","",INDEX(exp_year,MATCH(12,exp_wishno,0)))) | F18: =IF($A18="","",IF(INDEX(exp_month,MATCH(12,exp_wishno,0))="","",INDEX(exp_month,MATCH(12,exp_wishno,0)))) | G18: =IF($A18="","",IF(INDEX(exp_plan,MATCH(12,exp_wishno,0))="","",INDEX(exp_plan,MATCH(12,exp_wishno,0)))) | H18: =IF($A18="","",IF(INDEX(exp_fact,MATCH(12,exp_wishno,0))="","",INDEX(exp_fact,MATCH(12,exp_wishno,0)))) | I18: =IF($A18="","",IF(INDEX(exp_status,MATCH(12,exp_wishno,0))="","",INDEX(exp_status,MATCH(12,exp_wishno,0))))
A19: =IF(ISNA(MATCH(13,exp_wishno,0)),"",13) | B19: =IF($A19="","",IF(INDEX(exp_desc,MATCH(13,exp_wishno,0))="","",INDEX(exp_desc,MATCH(13,exp_wishno,0)))) | C19: =IF($A19="","",IF(INDEX(exp_cat,MATCH(13,exp_wishno,0))="","",INDEX(exp_cat,MATCH(13,exp_wishno,0)))) | D19: =IF($A19="","",IF(INDEX(exp_prio,MATCH(13,exp_wishno,0))="","",INDEX(exp_prio,MATCH(13,exp_wishno,0)))) | E19: =IF($A19="","",IF(INDEX(exp_year,MATCH(13,exp_wishno,0))="","",INDEX(exp_year,MATCH(13,exp_wishno,0)))) | F19: =IF($A19="","",IF(INDEX(exp_month,MATCH(13,exp_wishno,0))="","",INDEX(exp_month,MATCH(13,exp_wishno,0)))) | G19: =IF($A19="","",IF(INDEX(exp_plan,MATCH(13,exp_wishno,0))="","",INDEX(exp_plan,MATCH(13,exp_wishno,0)))) | H19: =IF($A19="","",IF(INDEX(exp_fact,MATCH(13,exp_wishno,0))="","",INDEX(exp_fact,MATCH(13,exp_wishno,0)))) | I19: =IF($A19="","",IF(INDEX(exp_status,MATCH(13,exp_wishno,0))="","",INDEX(exp_status,MATCH(13,exp_wishno,0))))
A20: =IF(ISNA(MATCH(14,exp_wishno,0)),"",14) | B20: =IF($A20="","",IF(INDEX(exp_desc,MATCH(14,exp_wishno,0))="","",INDEX(exp_desc,MATCH(14,exp_wishno,0)))) | C20: =IF($A20="","",IF(INDEX(exp_cat,MATCH(14,exp_wishno,0))="","",INDEX(exp_cat,MATCH(14,exp_wishno,0)))) | D20: =IF($A20="","",IF(INDEX(exp_prio,MATCH(14,exp_wishno,0))="","",INDEX(exp_prio,MATCH(14,exp_wishno,0)))) | E20: =IF($A20="","",IF(INDEX(exp_year,MATCH(14,exp_wishno,0))="","",INDEX(exp_year,MATCH(14,exp_wishno,0)))) | F20: =IF($A20="","",IF(INDEX(exp_month,MATCH(14,exp_wishno,0))="","",INDEX(exp_month,MATCH(14,exp_wishno,0)))) | G20: =IF($A20="","",IF(INDEX(exp_plan,MATCH(14,exp_wishno,0))="","",INDEX(exp_plan,MATCH(14,exp_wishno,0)))) | H20: =IF($A20="","",IF(INDEX(exp_fact,MATCH(14,exp_wishno,0))="","",INDEX(exp_fact,MATCH(14,exp_wishno,0)))) | I20: =IF($A20="","",IF(INDEX(exp_status,MATCH(14,exp_wishno,0))="","",INDEX(exp_status,MATCH(14,exp_wishno,0))))
A21: =IF(ISNA(MATCH(15,exp_wishno,0)),"",15) | B21: =IF($A21="","",IF(INDEX(exp_desc,MATCH(15,exp_wishno,0))="","",INDEX(exp_desc,MATCH(15,exp_wishno,0)))) | C21: =IF($A21="","",IF(INDEX(exp_cat,MATCH(15,exp_wishno,0))="","",INDEX(exp_cat,MATCH(15,exp_wishno,0)))) | D21: =IF($A21="","",IF(INDEX(exp_prio,MATCH(15,exp_wishno,0))="","",INDEX(exp_prio,MATCH(15,exp_wishno,0)))) | E21: =IF($A21="","",IF(INDEX(exp_year,MATCH(15,exp_wishno,0))="","",INDEX(exp_year,MATCH(15,exp_wishno,0)))) | F21: =IF($A21="","",IF(INDEX(exp_month,MATCH(15,exp_wishno,0))="","",INDEX(exp_month,MATCH(15,exp_wishno,0)))) | G21: =IF($A21="","",IF(INDEX(exp_plan,MATCH(15,exp_wishno,0))="","",INDEX(exp_plan,MATCH(15,exp_wishno,0)))) | H21: =IF($A21="","",IF(INDEX(exp_fact,MATCH(15,exp_wishno,0))="","",INDEX(exp_fact,MATCH(15,exp_wishno,0)))) | I21: =IF($A21="","",IF(INDEX(exp_status,MATCH(15,exp_wishno,0))="","",INDEX(exp_status,MATCH(15,exp_wishno,0))))
A22: =IF(ISNA(MATCH(16,exp_wishno,0)),"",16) | B22: =IF($A22="","",IF(INDEX(exp_desc,MATCH(16,exp_wishno,0))="","",INDEX(exp_desc,MATCH(16,exp_wishno,0)))) | C22: =IF($A22="","",IF(INDEX(exp_cat,MATCH(16,exp_wishno,0))="","",INDEX(exp_cat,MATCH(16,exp_wishno,0)))) | D22: =IF($A22="","",IF(INDEX(exp_prio,MATCH(16,exp_wishno,0))="","",INDEX(exp_prio,MATCH(16,exp_wishno,0)))) | E22: =IF($A22="","",IF(INDEX(exp_year,MATCH(16,exp_wishno,0))="","",INDEX(exp_year,MATCH(16,exp_wishno,0)))) | F22: =IF($A22="","",IF(INDEX(exp_month,MATCH(16,exp_wishno,0))="","",INDEX(exp_month,MATCH(16,exp_wishno,0)))) | G22: =IF($A22="","",IF(INDEX(exp_plan,MATCH(16,exp_wishno,0))="","",INDEX(exp_plan,MATCH(16,exp_wishno,0)))) | H22: =IF($A22="","",IF(INDEX(exp_fact,MATCH(16,exp_wishno,0))="","",INDEX(exp_fact,MATCH(16,exp_wishno,0)))) | I22: =IF($A22="","",IF(INDEX(exp_status,MATCH(16,exp_wishno,0))="","",INDEX(exp_status,MATCH(16,exp_wishno,0))))
A23: =IF(ISNA(MATCH(17,exp_wishno,0)),"",17) | B23: =IF($A23="","",IF(INDEX(exp_desc,MATCH(17,exp_wishno,0))="","",INDEX(exp_desc,MATCH(17,exp_wishno,0)))) | C23: =IF($A23="","",IF(INDEX(exp_cat,MATCH(17,exp_wishno,0))="","",INDEX(exp_cat,MATCH(17,exp_wishno,0)))) | D23: =IF($A23="","",IF(INDEX(exp_prio,MATCH(17,exp_wishno,0))="","",INDEX(exp_prio,MATCH(17,exp_wishno,0)))) | E23: =IF($A23="","",IF(INDEX(exp_year,MATCH(17,exp_wishno,0))="","",INDEX(exp_year,MATCH(17,exp_wishno,0)))) | F23: =IF($A23="","",IF(INDEX(exp_month,MATCH(17,exp_wishno,0))="","",INDEX(exp_month,MATCH(17,exp_wishno,0)))) | G23: =IF($A23="","",IF(INDEX(exp_plan,MATCH(17,exp_wishno,0))="","",INDEX(exp_plan,MATCH(17,exp_wishno,0)))) | H23: =IF($A23="","",IF(INDEX(exp_fact,MATCH(17,exp_wishno,0))="","",INDEX(exp_fact,MATCH(17,exp_wishno,0)))) | I23: =IF($A23="","",IF(INDEX(exp_status,MATCH(17,exp_wishno,0))="","",INDEX(exp_status,MATCH(17,exp_wishno,0))))
A24: =IF(ISNA(MATCH(18,exp_wishno,0)),"",18) | B24: =IF($A24="","",IF(INDEX(exp_desc,MATCH(18,exp_wishno,0))="","",INDEX(exp_desc,MATCH(18,exp_wishno,0)))) | C24: =IF($A24="","",IF(INDEX(exp_cat,MATCH(18,exp_wishno,0))="","",INDEX(exp_cat,MATCH(18,exp_wishno,0)))) | D24: =IF($A24="","",IF(INDEX(exp_prio,MATCH(18,exp_wishno,0))="","",INDEX(exp_prio,MATCH(18,exp_wishno,0)))) | E24: =IF($A24="","",IF(INDEX(exp_year,MATCH(18,exp_wishno,0))="","",INDEX(exp_year,MATCH(18,exp_wishno,0)))) | F24: =IF($A24="","",IF(INDEX(exp_month,MATCH(18,exp_wishno,0))="","",INDEX(exp_month,MATCH(18,exp_wishno,0)))) | G24: =IF($A24="","",IF(INDEX(exp_plan,MATCH(18,exp_wishno,0))="","",INDEX(exp_plan,MATCH(18,exp_wishno,0)))) | H24: =IF($A24="","",IF(INDEX(exp_fact,MATCH(18,exp_wishno,0))="","",INDEX(exp_fact,MATCH(18,exp_wishno,0)))) | I24: =IF($A24="","",IF(INDEX(exp_status,MATCH(18,exp_wishno,0))="","",INDEX(exp_status,MATCH(18,exp_wishno,0))))
A25: =IF(ISNA(MATCH(19,exp_wishno,0)),"",19) | B25: =IF($A25="","",IF(INDEX(exp_desc,MATCH(19,exp_wishno,0))="","",INDEX(exp_desc,MATCH(19,exp_wishno,0)))) | C25: =IF($A25="","",IF(INDEX(exp_cat,MATCH(19,exp_wishno,0))="","",INDEX(exp_cat,MATCH(19,exp_wishno,0)))) | D25: =IF($A25="","",IF(INDEX(exp_prio,MATCH(19,exp_wishno,0))="","",INDEX(exp_prio,MATCH(19,exp_wishno,0)))) | E25: =IF($A25="","",IF(INDEX(exp_year,MATCH(19,exp_wishno,0))="","",INDEX(exp_year,MATCH(19,exp_wishno,0)))) | F25: =IF($A25="","",IF(INDEX(exp_month,MATCH(19,exp_wishno,0))="","",INDEX(exp_month,MATCH(19,exp_wishno,0)))) | G25: =IF($A25="","",IF(INDEX(exp_plan,MATCH(19,exp_wishno,0))="","",INDEX(exp_plan,MATCH(19,exp_wishno,0)))) | H25: =IF($A25="","",IF(INDEX(exp_fact,MATCH(19,exp_wishno,0))="","",INDEX(exp_fact,MATCH(19,exp_wishno,0)))) | I25: =IF($A25="","",IF(INDEX(exp_status,MATCH(19,exp_wishno,0))="","",INDEX(exp_status,MATCH(19,exp_wishno,0))))
A26: =IF(ISNA(MATCH(20,exp_wishno,0)),"",20) | B26: =IF($A26="","",IF(INDEX(exp_desc,MATCH(20,exp_wishno,0))="","",INDEX(exp_desc,MATCH(20,exp_wishno,0)))) | C26: =IF($A26="","",IF(INDEX(exp_cat,MATCH(20,exp_wishno,0))="","",INDEX(exp_cat,MATCH(20,exp_wishno,0)))) | D26: =IF($A26="","",IF(INDEX(exp_prio,MATCH(20,exp_wishno,0))="","",INDEX(exp_prio,MATCH(20,exp_wishno,0)))) | E26: =IF($A26="","",IF(INDEX(exp_year,MATCH(20,exp_wishno,0))="","",INDEX(exp_year,MATCH(20,exp_wishno,0)))) | F26: =IF($A26="","",IF(INDEX(exp_month,MATCH(20,exp_wishno,0))="","",INDEX(exp_month,MATCH(20,exp_wishno,0)))) | G26: =IF($A26="","",IF(INDEX(exp_plan,MATCH(20,exp_wishno,0))="","",INDEX(exp_plan,MATCH(20,exp_wishno,0)))) | H26: =IF($A26="","",IF(INDEX(exp_fact,MATCH(20,exp_wishno,0))="","",INDEX(exp_fact,MATCH(20,exp_wishno,0)))) | I26: =IF($A26="","",IF(INDEX(exp_status,MATCH(20,exp_wishno,0))="","",INDEX(exp_status,MATCH(20,exp_wishno,0))))
A27: =IF(ISNA(MATCH(21,exp_wishno,0)),"",21) | B27: =IF($A27="","",IF(INDEX(exp_desc,MATCH(21,exp_wishno,0))="","",INDEX(exp_desc,MATCH(21,exp_wishno,0)))) | C27: =IF($A27="","",IF(INDEX(exp_cat,MATCH(21,exp_wishno,0))="","",INDEX(exp_cat,MATCH(21,exp_wishno,0)))) | D27: =IF($A27="","",IF(INDEX(exp_prio,MATCH(21,exp_wishno,0))="","",INDEX(exp_prio,MATCH(21,exp_wishno,0)))) | E27: =IF($A27="","",IF(INDEX(exp_year,MATCH(21,exp_wishno,0))="","",INDEX(exp_year,MATCH(21,exp_wishno,0)))) | F27: =IF($A27="","",IF(INDEX(exp_month,MATCH(21,exp_wishno,0))="","",INDEX(exp_month,MATCH(21,exp_wishno,0)))) | G27: =IF($A27="","",IF(INDEX(exp_plan,MATCH(21,exp_wishno,0))="","",INDEX(exp_plan,MATCH(21,exp_wishno,0)))) | H27: =IF($A27="","",IF(INDEX(exp_fact,MATCH(21,exp_wishno,0))="","",INDEX(exp_fact,MATCH(21,exp_wishno,0)))) | I27: =IF($A27="","",IF(INDEX(exp_status,MATCH(21,exp_wishno,0))="","",INDEX(exp_status,MATCH(21,exp_wishno,0))))
A28: =IF(ISNA(MATCH(22,exp_wishno,0)),"",22) | B28: =IF($A28="","",IF(INDEX(exp_desc,MATCH(22,exp_wishno,0))="","",INDEX(exp_desc,MATCH(22,exp_wishno,0)))) | C28: =IF($A28="","",IF(INDEX(exp_cat,MATCH(22,exp_wishno,0))="","",INDEX(exp_cat,MATCH(22,exp_wishno,0)))) | D28: =IF($A28="","",IF(INDEX(exp_prio,MATCH(22,exp_wishno,0))="","",INDEX(exp_prio,MATCH(22,exp_wishno,0)))) | E28: =IF($A28="","",IF(INDEX(exp_year,MATCH(22,exp_wishno,0))="","",INDEX(exp_year,MATCH(22,exp_wishno,0)))) | F28: =IF($A28="","",IF(INDEX(exp_month,MATCH(22,exp_wishno,0))="","",INDEX(exp_month,MATCH(22,exp_wishno,0)))) | G28: =IF($A28="","",IF(INDEX(exp_plan,MATCH(22,exp_wishno,0))="","",INDEX(exp_plan,MATCH(22,exp_wishno,0)))) | H28: =IF($A28="","",IF(INDEX(exp_fact,MATCH(22,exp_wishno,0))="","",INDEX(exp_fact,MATCH(22,exp_wishno,0)))) | I28: =IF($A28="","",IF(INDEX(exp_status,MATCH(22,exp_wishno,0))="","",INDEX(exp_status,MATCH(22,exp_wishno,0))))
A29: =IF(ISNA(MATCH(23,exp_wishno,0)),"",23) | B29: =IF($A29="","",IF(INDEX(exp_desc,MATCH(23,exp_wishno,0))="","",INDEX(exp_desc,MATCH(23,exp_wishno,0)))) | C29: =IF($A29="","",IF(INDEX(exp_cat,MATCH(23,exp_wishno,0))="","",INDEX(exp_cat,MATCH(23,exp_wishno,0)))) | D29: =IF($A29="","",IF(INDEX(exp_prio,MATCH(23,exp_wishno,0))="","",INDEX(exp_prio,MATCH(23,exp_wishno,0)))) | E29: =IF($A29="","",IF(INDEX(exp_year,MATCH(23,exp_wishno,0))="","",INDEX(exp_year,MATCH(23,exp_wishno,0)))) | F29: =IF($A29="","",IF(INDEX(exp_month,MATCH(23,exp_wishno,0))="","",INDEX(exp_month,MATCH(23,exp_wishno,0)))) | G29: =IF($A29="","",IF(INDEX(exp_plan,MATCH(23,exp_wishno,0))="","",INDEX(exp_plan,MATCH(23,exp_wishno,0)))) | H29: =IF($A29="","",IF(INDEX(exp_fact,MATCH(23,exp_wishno,0))="","",INDEX(exp_fact,MATCH(23,exp_wishno,0)))) | I29: =IF($A29="","",IF(INDEX(exp_status,MATCH(23,exp_wishno,0))="","",INDEX(exp_status,MATCH(23,exp_wishno,0))))
A30: =IF(ISNA(MATCH(24,exp_wishno,0)),"",24) | B30: =IF($A30="","",IF(INDEX(exp_desc,MATCH(24,exp_wishno,0))="","",INDEX(exp_desc,MATCH(24,exp_wishno,0)))) | C30: =IF($A30="","",IF(INDEX(exp_cat,MATCH(24,exp_wishno,0))="","",INDEX(exp_cat,MATCH(24,exp_wishno,0)))) | D30: =IF($A30="","",IF(INDEX(exp_prio,MATCH(24,exp_wishno,0))="","",INDEX(exp_prio,MATCH(24,exp_wishno,0)))) | E30: =IF($A30="","",IF(INDEX(exp_year,MATCH(24,exp_wishno,0))="","",INDEX(exp_year,MATCH(24,exp_wishno,0)))) | F30: =IF($A30="","",IF(INDEX(exp_month,MATCH(24,exp_wishno,0))="","",INDEX(exp_month,MATCH(24,exp_wishno,0)))) | G30: =IF($A30="","",IF(INDEX(exp_plan,MATCH(24,exp_wishno,0))="","",INDEX(exp_plan,MATCH(24,exp_wishno,0)))) | H30: =IF($A30="","",IF(INDEX(exp_fact,MATCH(24,exp_wishno,0))="","",INDEX(exp_fact,MATCH(24,exp_wishno,0)))) | I30: =IF($A30="","",IF(INDEX(exp_status,MATCH(24,exp_wishno,0))="","",INDEX(exp_status,MATCH(24,exp_wishno,0))))
A31: =IF(ISNA(MATCH(25,exp_wishno,0)),"",25) | B31: =IF($A31="","",IF(INDEX(exp_desc,MATCH(25,exp_wishno,0))="","",INDEX(exp_desc,MATCH(25,exp_wishno,0)))) | C31: =IF($A31="","",IF(INDEX(exp_cat,MATCH(25,exp_wishno,0))="","",INDEX(exp_cat,MATCH(25,exp_wishno,0)))) | D31: =IF($A31="","",IF(INDEX(exp_prio,MATCH(25,exp_wishno,0))="","",INDEX(exp_prio,MATCH(25,exp_wishno,0)))) | E31: =IF($A31="","",IF(INDEX(exp_year,MATCH(25,exp_wishno,0))="","",INDEX(exp_year,MATCH(25,exp_wishno,0)))) | F31: =IF($A31="","",IF(INDEX(exp_month,MATCH(25,exp_wishno,0))="","",INDEX(exp_month,MATCH(25,exp_wishno,0)))) | G31: =IF($A31="","",IF(INDEX(exp_plan,MATCH(25,exp_wishno,0))="","",INDEX(exp_plan,MATCH(25,exp_wishno,0)))) | H31: =IF($A31="","",IF(INDEX(exp_fact,MATCH(25,exp_wishno,0))="","",INDEX(exp_fact,MATCH(25,exp_wishno,0)))) | I31: =IF($A31="","",IF(INDEX(exp_status,MATCH(25,exp_wishno,0))="","",INDEX(exp_status,MATCH(25,exp_wishno,0))))
A32: =IF(ISNA(MATCH(26,exp_wishno,0)),"",26) | B32: =IF($A32="","",IF(INDEX(exp_desc,MATCH(26,exp_wishno,0))="","",INDEX(exp_desc,MATCH(26,exp_wishno,0)))) | C32: =IF($A32="","",IF(INDEX(exp_cat,MATCH(26,exp_wishno,0))="","",INDEX(exp_cat,MATCH(26,exp_wishno,0)))) | D32: =IF($A32="","",IF(INDEX(exp_prio,MATCH(26,exp_wishno,0))="","",INDEX(exp_prio,MATCH(26,exp_wishno,0)))) | E32: =IF($A32="","",IF(INDEX(exp_year,MATCH(26,exp_wishno,0))="","",INDEX(exp_year,MATCH(26,exp_wishno,0)))) | F32: =IF($A32="","",IF(INDEX(exp_month,MATCH(26,exp_wishno,0))="","",INDEX(exp_month,MATCH(26,exp_wishno,0)))) | G32: =IF($A32="","",IF(INDEX(exp_plan,MATCH(26,exp_wishno,0))="","",INDEX(exp_plan,MATCH(26,exp_wishno,0)))) | H32: =IF($A32="","",IF(INDEX(exp_fact,MATCH(26,exp_wishno,0))="","",INDEX(exp_fact,MATCH(26,exp_wishno,0)))) | I32: =IF($A32="","",IF(INDEX(exp_status,MATCH(26,exp_wishno,0))="","",INDEX(exp_status,MATCH(26,exp_wishno,0))))
A33: =IF(ISNA(MATCH(27,exp_wishno,0)),"",27) | B33: =IF($A33="","",IF(INDEX(exp_desc,MATCH(27,exp_wishno,0))="","",INDEX(exp_desc,MATCH(27,exp_wishno,0)))) | C33: =IF($A33="","",IF(INDEX(exp_cat,MATCH(27,exp_wishno,0))="","",INDEX(exp_cat,MATCH(27,exp_wishno,0)))) | D33: =IF($A33="","",IF(INDEX(exp_prio,MATCH(27,exp_wishno,0))="","",INDEX(exp_prio,MATCH(27,exp_wishno,0)))) | E33: =IF($A33="","",IF(INDEX(exp_year,MATCH(27,exp_wishno,0))="","",INDEX(exp_year,MATCH(27,exp_wishno,0)))) | F33: =IF($A33="","",IF(INDEX(exp_month,MATCH(27,exp_wishno,0))="","",INDEX(exp_month,MATCH(27,exp_wishno,0)))) | G33: =IF($A33="","",IF(INDEX(exp_plan,MATCH(27,exp_wishno,0))="","",INDEX(exp_plan,MATCH(27,exp_wishno,0)))) | H33: =IF($A33="","",IF(INDEX(exp_fact,MATCH(27,exp_wishno,0))="","",INDEX(exp_fact,MATCH(27,exp_wishno,0)))) | I33: =IF($A33="","",IF(INDEX(exp_status,MATCH(27,exp_wishno,0))="","",INDEX(exp_status,MATCH(27,exp_wishno,0))))
A34: =IF(ISNA(MATCH(28,exp_wishno,0)),"",28) | B34: =IF($A34="","",IF(INDEX(exp_desc,MATCH(28,exp_wishno,0))="","",INDEX(exp_desc,MATCH(28,exp_wishno,0)))) | C34: =IF($A34="","",IF(INDEX(exp_cat,MATCH(28,exp_wishno,0))="","",INDEX(exp_cat,MATCH(28,exp_wishno,0)))) | D34: =IF($A34="","",IF(INDEX(exp_prio,MATCH(28,exp_wishno,0))="","",INDEX(exp_prio,MATCH(28,exp_wishno,0)))) | E34: =IF($A34="","",IF(INDEX(exp_year,MATCH(28,exp_wishno,0))="","",INDEX(exp_year,MATCH(28,exp_wishno,0)))) | F34: =IF($A34="","",IF(INDEX(exp_month,MATCH(28,exp_wishno,0))="","",INDEX(exp_month,MATCH(28,exp_wishno,0)))) | G34: =IF($A34="","",IF(INDEX(exp_plan,MATCH(28,exp_wishno,0))="","",INDEX(exp_plan,MATCH(28,exp_wishno,0)))) | H34: =IF($A34="","",IF(INDEX(exp_fact,MATCH(28,exp_wishno,0))="","",INDEX(exp_fact,MATCH(28,exp_wishno,0)))) | I34: =IF($A34="","",IF(INDEX(exp_status,MATCH(28,exp_wishno,0))="","",INDEX(exp_status,MATCH(28,exp_wishno,0))))
A35: =IF(ISNA(MATCH(29,exp_wishno,0)),"",29) | B35: =IF($A35="","",IF(INDEX(exp_desc,MATCH(29,exp_wishno,0))="","",INDEX(exp_desc,MATCH(29,exp_wishno,0)))) | C35: =IF($A35="","",IF(INDEX(exp_cat,MATCH(29,exp_wishno,0))="","",INDEX(exp_cat,MATCH(29,exp_wishno,0)))) | D35: =IF($A35="","",IF(INDEX(exp_prio,MATCH(29,exp_wishno,0))="","",INDEX(exp_prio,MATCH(29,exp_wishno,0)))) | E35: =IF($A35="","",IF(INDEX(exp_year,MATCH(29,exp_wishno,0))="","",INDEX(exp_year,MATCH(29,exp_wishno,0)))) | F35: =IF($A35="","",IF(INDEX(exp_month,MATCH(29,exp_wishno,0))="","",INDEX(exp_month,MATCH(29,exp_wishno,0)))) | G35: =IF($A35="","",IF(INDEX(exp_plan,MATCH(29,exp_wishno,0))="","",INDEX(exp_plan,MATCH(29,exp_wishno,0)))) | H35: =IF($A35="","",IF(INDEX(exp_fact,MATCH(29,exp_wishno,0))="","",INDEX(exp_fact,MATCH(29,exp_wishno,0)))) | I35: =IF($A35="","",IF(INDEX(exp_status,MATCH(29,exp_wishno,0))="","",INDEX(exp_status,MATCH(29,exp_wishno,0))))
A36: =IF(ISNA(MATCH(30,exp_wishno,0)),"",30) | B36: =IF($A36="","",IF(INDEX(exp_desc,MATCH(30,exp_wishno,0))="","",INDEX(exp_desc,MATCH(30,exp_wishno,0)))) | C36: =IF($A36="","",IF(INDEX(exp_cat,MATCH(30,exp_wishno,0))="","",INDEX(exp_cat,MATCH(30,exp_wishno,0)))) | D36: =IF($A36="","",IF(INDEX(exp_prio,MATCH(30,exp_wishno,0))="","",INDEX(exp_prio,MATCH(30,exp_wishno,0)))) | E36: =IF($A36="","",IF(INDEX(exp_year,MATCH(30,exp_wishno,0))="","",INDEX(exp_year,MATCH(30,exp_wishno,0)))) | F36: =IF($A36="","",IF(INDEX(exp_month,MATCH(30,exp_wishno,0))="","",INDEX(exp_month,MATCH(30,exp_wishno,0)))) | G36: =IF($A36="","",IF(INDEX(exp_plan,MATCH(30,exp_wishno,0))="","",INDEX(exp_plan,MATCH(30,exp_wishno,0)))) | H36: =IF($A36="","",IF(INDEX(exp_fact,MATCH(30,exp_wishno,0))="","",INDEX(exp_fact,MATCH(30,exp_wishno,0)))) | I36: =IF($A36="","",IF(INDEX(exp_status,MATCH(30,exp_wishno,0))="","",INDEX(exp_status,MATCH(30,exp_wishno,0))))
A37: =IF(ISNA(MATCH(31,exp_wishno,0)),"",31) | B37: =IF($A37="","",IF(INDEX(exp_desc,MATCH(31,exp_wishno,0))="","",INDEX(exp_desc,MATCH(31,exp_wishno,0)))) | C37: =IF($A37="","",IF(INDEX(exp_cat,MATCH(31,exp_wishno,0))="","",INDEX(exp_cat,MATCH(31,exp_wishno,0)))) | D37: =IF($A37="","",IF(INDEX(exp_prio,MATCH(31,exp_wishno,0))="","",INDEX(exp_prio,MATCH(31,exp_wishno,0)))) | E37: =IF($A37="","",IF(INDEX(exp_year,MATCH(31,exp_wishno,0))="","",INDEX(exp_year,MATCH(31,exp_wishno,0)))) | F37: =IF($A37="","",IF(INDEX(exp_month,MATCH(31,exp_wishno,0))="","",INDEX(exp_month,MATCH(31,exp_wishno,0)))) | G37: =IF($A37="","",IF(INDEX(exp_plan,MATCH(31,exp_wishno,0))="","",INDEX(exp_plan,MATCH(31,exp_wishno,0)))) | H37: =IF($A37="","",IF(INDEX(exp_fact,MATCH(31,exp_wishno,0))="","",INDEX(exp_fact,MATCH(31,exp_wishno,0)))) | I37: =IF($A37="","",IF(INDEX(exp_status,MATCH(31,exp_wishno,0))="","",INDEX(exp_status,MATCH(31,exp_wishno,0))))
A38: =IF(ISNA(MATCH(32,exp_wishno,0)),"",32) | B38: =IF($A38="","",IF(INDEX(exp_desc,MATCH(32,exp_wishno,0))="","",INDEX(exp_desc,MATCH(32,exp_wishno,0)))) | C38: =IF($A38="","",IF(INDEX(exp_cat,MATCH(32,exp_wishno,0))="","",INDEX(exp_cat,MATCH(32,exp_wishno,0)))) | D38: =IF($A38="","",IF(INDEX(exp_prio,MATCH(32,exp_wishno,0))="","",INDEX(exp_prio,MATCH(32,exp_wishno,0)))) | E38: =IF($A38="","",IF(INDEX(exp_year,MATCH(32,exp_wishno,0))="","",INDEX(exp_year,MATCH(32,exp_wishno,0)))) | F38: =IF($A38="","",IF(INDEX(exp_month,MATCH(32,exp_wishno,0))="","",INDEX(exp_month,MATCH(32,exp_wishno,0)))) | G38: =IF($A38="","",IF(INDEX(exp_plan,MATCH(32,exp_wishno,0))="","",INDEX(exp_plan,MATCH(32,exp_wishno,0)))) | H38: =IF($A38="","",IF(INDEX(exp_fact,MATCH(32,exp_wishno,0))="","",INDEX(exp_fact,MATCH(32,exp_wishno,0)))) | I38: =IF($A38="","",IF(INDEX(exp_status,MATCH(32,exp_wishno,0))="","",INDEX(exp_status,MATCH(32,exp_wishno,0))))
A39: =IF(ISNA(MATCH(33,exp_wishno,0)),"",33) | B39: =IF($A39="","",IF(INDEX(exp_desc,MATCH(33,exp_wishno,0))="","",INDEX(exp_desc,MATCH(33,exp_wishno,0)))) | C39: =IF($A39="","",IF(INDEX(exp_cat,MATCH(33,exp_wishno,0))="","",INDEX(exp_cat,MATCH(33,exp_wishno,0)))) | D39: =IF($A39="","",IF(INDEX(exp_prio,MATCH(33,exp_wishno,0))="","",INDEX(exp_prio,MATCH(33,exp_wishno,0)))) | E39: =IF($A39="","",IF(INDEX(exp_year,MATCH(33,exp_wishno,0))="","",INDEX(exp_year,MATCH(33,exp_wishno,0)))) | F39: =IF($A39="","",IF(INDEX(exp_month,MATCH(33,exp_wishno,0))="","",INDEX(exp_month,MATCH(33,exp_wishno,0)))) | G39: =IF($A39="","",IF(INDEX(exp_plan,MATCH(33,exp_wishno,0))="","",INDEX(exp_plan,MATCH(33,exp_wishno,0)))) | H39: =IF($A39="","",IF(INDEX(exp_fact,MATCH(33,exp_wishno,0))="","",INDEX(exp_fact,MATCH(33,exp_wishno,0)))) | I39: =IF($A39="","",IF(INDEX(exp_status,MATCH(33,exp_wishno,0))="","",INDEX(exp_status,MATCH(33,exp_wishno,0))))
A40: =IF(ISNA(MATCH(34,exp_wishno,0)),"",34) | B40: =IF($A40="","",IF(INDEX(exp_desc,MATCH(34,exp_wishno,0))="","",INDEX(exp_desc,MATCH(34,exp_wishno,0)))) | C40: =IF($A40="","",IF(INDEX(exp_cat,MATCH(34,exp_wishno,0))="","",INDEX(exp_cat,MATCH(34,exp_wishno,0)))) | D40: =IF($A40="","",IF(INDEX(exp_prio,MATCH(34,exp_wishno,0))="","",INDEX(exp_prio,MATCH(34,exp_wishno,0)))) | E40: =IF($A40="","",IF(INDEX(exp_year,MATCH(34,exp_wishno,0))="","",INDEX(exp_year,MATCH(34,exp_wishno,0)))) | F40: =IF($A40="","",IF(INDEX(exp_month,MATCH(34,exp_wishno,0))="","",INDEX(exp_month,MATCH(34,exp_wishno,0)))) | G40: =IF($A40="","",IF(INDEX(exp_plan,MATCH(34,exp_wishno,0))="","",INDEX(exp_plan,MATCH(34,exp_wishno,0)))) | H40: =IF($A40="","",IF(INDEX(exp_fact,MATCH(34,exp_wishno,0))="","",INDEX(exp_fact,MATCH(34,exp_wishno,0)))) | I40: =IF($A40="","",IF(INDEX(exp_status,MATCH(34,exp_wishno,0))="","",INDEX(exp_status,MATCH(34,exp_wishno,0))))
A41: =IF(ISNA(MATCH(35,exp_wishno,0)),"",35) | B41: =IF($A41="","",IF(INDEX(exp_desc,MATCH(35,exp_wishno,0))="","",INDEX(exp_desc,MATCH(35,exp_wishno,0)))) | C41: =IF($A41="","",IF(INDEX(exp_cat,MATCH(35,exp_wishno,0))="","",INDEX(exp_cat,MATCH(35,exp_wishno,0)))) | D41: =IF($A41="","",IF(INDEX(exp_prio,MATCH(35,exp_wishno,0))="","",INDEX(exp_prio,MATCH(35,exp_wishno,0)))) | E41: =IF($A41="","",IF(INDEX(exp_year,MATCH(35,exp_wishno,0))="","",INDEX(exp_year,MATCH(35,exp_wishno,0)))) | F41: =IF($A41="","",IF(INDEX(exp_month,MATCH(35,exp_wishno,0))="","",INDEX(exp_month,MATCH(35,exp_wishno,0)))) | G41: =IF($A41="","",IF(INDEX(exp_plan,MATCH(35,exp_wishno,0))="","",INDEX(exp_plan,MATCH(35,exp_wishno,0)))) | H41: =IF($A41="","",IF(INDEX(exp_fact,MATCH(35,exp_wishno,0))="","",INDEX(exp_fact,MATCH(35,exp_wishno,0)))) | I41: =IF($A41="","",IF(INDEX(exp_status,MATCH(35,exp_wishno,0))="","",INDEX(exp_status,MATCH(35,exp_wishno,0))))
A42: =IF(ISNA(MATCH(36,exp_wishno,0)),"",36) | B42: =IF($A42="","",IF(INDEX(exp_desc,MATCH(36,exp_wishno,0))="","",INDEX(exp_desc,MATCH(36,exp_wishno,0)))) | C42: =IF($A42="","",IF(INDEX(exp_cat,MATCH(36,exp_wishno,0))="","",INDEX(exp_cat,MATCH(36,exp_wishno,0)))) | D42: =IF($A42="","",IF(INDEX(exp_prio,MATCH(36,exp_wishno,0))="","",INDEX(exp_prio,MATCH(36,exp_wishno,0)))) | E42: =IF($A42="","",IF(INDEX(exp_year,MATCH(36,exp_wishno,0))="","",INDEX(exp_year,MATCH(36,exp_wishno,0)))) | F42: =IF($A42="","",IF(INDEX(exp_month,MATCH(36,exp_wishno,0))="","",INDEX(exp_month,MATCH(36,exp_wishno,0)))) | G42: =IF($A42="","",IF(INDEX(exp_plan,MATCH(36,exp_wishno,0))="","",INDEX(exp_plan,MATCH(36,exp_wishno,0)))) | H42: =IF($A42="","",IF(INDEX(exp_fact,MATCH(36,exp_wishno,0))="","",INDEX(exp_fact,MATCH(36,exp_wishno,0)))) | I42: =IF($A42="","",IF(INDEX(exp_status,MATCH(36,exp_wishno,0))="","",INDEX(exp_status,MATCH(36,exp_wishno,0))))
A43: =IF(ISNA(MATCH(37,exp_wishno,0)),"",37) | B43: =IF($A43="","",IF(INDEX(exp_desc,MATCH(37,exp_wishno,0))="","",INDEX(exp_desc,MATCH(37,exp_wishno,0)))) | C43: =IF($A43="","",IF(INDEX(exp_cat,MATCH(37,exp_wishno,0))="","",INDEX(exp_cat,MATCH(37,exp_wishno,0)))) | D43: =IF($A43="","",IF(INDEX(exp_prio,MATCH(37,exp_wishno,0))="","",INDEX(exp_prio,MATCH(37,exp_wishno,0)))) | E43: =IF($A43="","",IF(INDEX(exp_year,MATCH(37,exp_wishno,0))="","",INDEX(exp_year,MATCH(37,exp_wishno,0)))) | F43: =IF($A43="","",IF(INDEX(exp_month,MATCH(37,exp_wishno,0))="","",INDEX(exp_month,MATCH(37,exp_wishno,0)))) | G43: =IF($A43="","",IF(INDEX(exp_plan,MATCH(37,exp_wishno,0))="","",INDEX(exp_plan,MATCH(37,exp_wishno,0)))) | H43: =IF($A43="","",IF(INDEX(exp_fact,MATCH(37,exp_wishno,0))="","",INDEX(exp_fact,MATCH(37,exp_wishno,0)))) | I43: =IF($A43="","",IF(INDEX(exp_status,MATCH(37,exp_wishno,0))="","",INDEX(exp_status,MATCH(37,exp_wishno,0))))
A44: =IF(ISNA(MATCH(38,exp_wishno,0)),"",38) | B44: =IF($A44="","",IF(INDEX(exp_desc,MATCH(38,exp_wishno,0))="","",INDEX(exp_desc,MATCH(38,exp_wishno,0)))) | C44: =IF($A44="","",IF(INDEX(exp_cat,MATCH(38,exp_wishno,0))="","",INDEX(exp_cat,MATCH(38,exp_wishno,0)))) | D44: =IF($A44="","",IF(INDEX(exp_prio,MATCH(38,exp_wishno,0))="","",INDEX(exp_prio,MATCH(38,exp_wishno,0)))) | E44: =IF($A44="","",IF(INDEX(exp_year,MATCH(38,exp_wishno,0))="","",INDEX(exp_year,MATCH(38,exp_wishno,0)))) | F44: =IF($A44="","",IF(INDEX(exp_month,MATCH(38,exp_wishno,0))="","",INDEX(exp_month,MATCH(38,exp_wishno,0)))) | G44: =IF($A44="","",IF(INDEX(exp_plan,MATCH(38,exp_wishno,0))="","",INDEX(exp_plan,MATCH(38,exp_wishno,0)))) | H44: =IF($A44="","",IF(INDEX(exp_fact,MATCH(38,exp_wishno,0))="","",INDEX(exp_fact,MATCH(38,exp_wishno,0)))) | I44: =IF($A44="","",IF(INDEX(exp_status,MATCH(38,exp_wishno,0))="","",INDEX(exp_status,MATCH(38,exp_wishno,0))))
A45: =IF(ISNA(MATCH(39,exp_wishno,0)),"",39) | B45: =IF($A45="","",IF(INDEX(exp_desc,MATCH(39,exp_wishno,0))="","",INDEX(exp_desc,MATCH(39,exp_wishno,0)))) | C45: =IF($A45="","",IF(INDEX(exp_cat,MATCH(39,exp_wishno,0))="","",INDEX(exp_cat,MATCH(39,exp_wishno,0)))) | D45: =IF($A45="","",IF(INDEX(exp_prio,MATCH(39,exp_wishno,0))="","",INDEX(exp_prio,MATCH(39,exp_wishno,0)))) | E45: =IF($A45="","",IF(INDEX(exp_year,MATCH(39,exp_wishno,0))="","",INDEX(exp_year,MATCH(39,exp_wishno,0)))) | F45: =IF($A45="","",IF(INDEX(exp_month,MATCH(39,exp_wishno,0))="","",INDEX(exp_month,MATCH(39,exp_wishno,0)))) | G45: =IF($A45="","",IF(INDEX(exp_plan,MATCH(39,exp_wishno,0))="","",INDEX(exp_plan,MATCH(39,exp_wishno,0)))) | H45: =IF($A45="","",IF(INDEX(exp_fact,MATCH(39,exp_wishno,0))="","",INDEX(exp_fact,MATCH(39,exp_wishno,0)))) | I45: =IF($A45="","",IF(INDEX(exp_status,MATCH(39,exp_wishno,0))="","",INDEX(exp_status,MATCH(39,exp_wishno,0))))
A46: =IF(ISNA(MATCH(40,exp_wishno,0)),"",40) | B46: =IF($A46="","",IF(INDEX(exp_desc,MATCH(40,exp_wishno,0))="","",INDEX(exp_desc,MATCH(40,exp_wishno,0)))) | C46: =IF($A46="","",IF(INDEX(exp_cat,MATCH(40,exp_wishno,0))="","",INDEX(exp_cat,MATCH(40,exp_wishno,0)))) | D46: =IF($A46="","",IF(INDEX(exp_prio,MATCH(40,exp_wishno,0))="","",INDEX(exp_prio,MATCH(40,exp_wishno,0)))) | E46: =IF($A46="","",IF(INDEX(exp_year,MATCH(40,exp_wishno,0))="","",INDEX(exp_year,MATCH(40,exp_wishno,0)))) | F46: =IF($A46="","",IF(INDEX(exp_month,MATCH(40,exp_wishno,0))="","",INDEX(exp_month,MATCH(40,exp_wishno,0)))) | G46: =IF($A46="","",IF(INDEX(exp_plan,MATCH(40,exp_wishno,0))="","",INDEX(exp_plan,MATCH(40,exp_wishno,0)))) | H46: =IF($A46="","",IF(INDEX(exp_fact,MATCH(40,exp_wishno,0))="","",INDEX(exp_fact,MATCH(40,exp_wishno,0)))) | I46: =IF($A46="","",IF(INDEX(exp_status,MATCH(40,exp_wishno,0))="","",INDEX(exp_status,MATCH(40,exp_wishno,0))))
A47: =IF(ISNA(MATCH(41,exp_wishno,0)),"",41) | B47: =IF($A47="","",IF(INDEX(exp_desc,MATCH(41,exp_wishno,0))="","",INDEX(exp_desc,MATCH(41,exp_wishno,0)))) | C47: =IF($A47="","",IF(INDEX(exp_cat,MATCH(41,exp_wishno,0))="","",INDEX(exp_cat,MATCH(41,exp_wishno,0)))) | D47: =IF($A47="","",IF(INDEX(exp_prio,MATCH(41,exp_wishno,0))="","",INDEX(exp_prio,MATCH(41,exp_wishno,0)))) | E47: =IF($A47="","",IF(INDEX(exp_year,MATCH(41,exp_wishno,0))="","",INDEX(exp_year,MATCH(41,exp_wishno,0)))) | F47: =IF($A47="","",IF(INDEX(exp_month,MATCH(41,exp_wishno,0))="","",INDEX(exp_month,MATCH(41,exp_wishno,0)))) | G47: =IF($A47="","",IF(INDEX(exp_plan,MATCH(41,exp_wishno,0))="","",INDEX(exp_plan,MATCH(41,exp_wishno,0)))) | H47: =IF($A47="","",IF(INDEX(exp_fact,MATCH(41,exp_wishno,0))="","",INDEX(exp_fact,MATCH(41,exp_wishno,0)))) | I47: =IF($A47="","",IF(INDEX(exp_status,MATCH(41,exp_wishno,0))="","",INDEX(exp_status,MATCH(41,exp_wishno,0))))
A48: =IF(ISNA(MATCH(42,exp_wishno,0)),"",42) | B48: =IF($A48="","",IF(INDEX(exp_desc,MATCH(42,exp_wishno,0))="","",INDEX(exp_desc,MATCH(42,exp_wishno,0)))) | C48: =IF($A48="","",IF(INDEX(exp_cat,MATCH(42,exp_wishno,0))="","",INDEX(exp_cat,MATCH(42,exp_wishno,0)))) | D48: =IF($A48="","",IF(INDEX(exp_prio,MATCH(42,exp_wishno,0))="","",INDEX(exp_prio,MATCH(42,exp_wishno,0)))) | E48: =IF($A48="","",IF(INDEX(exp_year,MATCH(42,exp_wishno,0))="","",INDEX(exp_year,MATCH(42,exp_wishno,0)))) | F48: =IF($A48="","",IF(INDEX(exp_month,MATCH(42,exp_wishno,0))="","",INDEX(exp_month,MATCH(42,exp_wishno,0)))) | G48: =IF($A48="","",IF(INDEX(exp_plan,MATCH(42,exp_wishno,0))="","",INDEX(exp_plan,MATCH(42,exp_wishno,0)))) | H48: =IF($A48="","",IF(INDEX(exp_fact,MATCH(42,exp_wishno,0))="","",INDEX(exp_fact,MATCH(42,exp_wishno,0)))) | I48: =IF($A48="","",IF(INDEX(exp_status,MATCH(42,exp_wishno,0))="","",INDEX(exp_status,MATCH(42,exp_wishno,0))))
A49: =IF(ISNA(MATCH(43,exp_wishno,0)),"",43) | B49: =IF($A49="","",IF(INDEX(exp_desc,MATCH(43,exp_wishno,0))="","",INDEX(exp_desc,MATCH(43,exp_wishno,0)))) | C49: =IF($A49="","",IF(INDEX(exp_cat,MATCH(43,exp_wishno,0))="","",INDEX(exp_cat,MATCH(43,exp_wishno,0)))) | D49: =IF($A49="","",IF(INDEX(exp_prio,MATCH(43,exp_wishno,0))="","",INDEX(exp_prio,MATCH(43,exp_wishno,0)))) | E49: =IF($A49="","",IF(INDEX(exp_year,MATCH(43,exp_wishno,0))="","",INDEX(exp_year,MATCH(43,exp_wishno,0)))) | F49: =IF($A49="","",IF(INDEX(exp_month,MATCH(43,exp_wishno,0))="","",INDEX(exp_month,MATCH(43,exp_wishno,0)))) | G49: =IF($A49="","",IF(INDEX(exp_plan,MATCH(43,exp_wishno,0))="","",INDEX(exp_plan,MATCH(43,exp_wishno,0)))) | H49: =IF($A49="","",IF(INDEX(exp_fact,MATCH(43,exp_wishno,0))="","",INDEX(exp_fact,MATCH(43,exp_wishno,0)))) | I49: =IF($A49="","",IF(INDEX(exp_status,MATCH(43,exp_wishno,0))="","",INDEX(exp_status,MATCH(43,exp_wishno,0))))
A50: =IF(ISNA(MATCH(44,exp_wishno,0)),"",44) | B50: =IF($A50="","",IF(INDEX(exp_desc,MATCH(44,exp_wishno,0))="","",INDEX(exp_desc,MATCH(44,exp_wishno,0)))) | C50: =IF($A50="","",IF(INDEX(exp_cat,MATCH(44,exp_wishno,0))="","",INDEX(exp_cat,MATCH(44,exp_wishno,0)))) | D50: =IF($A50="","",IF(INDEX(exp_prio,MATCH(44,exp_wishno,0))="","",INDEX(exp_prio,MATCH(44,exp_wishno,0)))) | E50: =IF($A50="","",IF(INDEX(exp_year,MATCH(44,exp_wishno,0))="","",INDEX(exp_year,MATCH(44,exp_wishno,0)))) | F50: =IF($A50="","",IF(INDEX(exp_month,MATCH(44,exp_wishno,0))="","",INDEX(exp_month,MATCH(44,exp_wishno,0)))) | G50: =IF($A50="","",IF(INDEX(exp_plan,MATCH(44,exp_wishno,0))="","",INDEX(exp_plan,MATCH(44,exp_wishno,0)))) | H50: =IF($A50="","",IF(INDEX(exp_fact,MATCH(44,exp_wishno,0))="","",INDEX(exp_fact,MATCH(44,exp_wishno,0)))) | I50: =IF($A50="","",IF(INDEX(exp_status,MATCH(44,exp_wishno,0))="","",INDEX(exp_status,MATCH(44,exp_wishno,0))))
A51: =IF(ISNA(MATCH(45,exp_wishno,0)),"",45) | B51: =IF($A51="","",IF(INDEX(exp_desc,MATCH(45,exp_wishno,0))="","",INDEX(exp_desc,MATCH(45,exp_wishno,0)))) | C51: =IF($A51="","",IF(INDEX(exp_cat,MATCH(45,exp_wishno,0))="","",INDEX(exp_cat,MATCH(45,exp_wishno,0)))) | D51: =IF($A51="","",IF(INDEX(exp_prio,MATCH(45,exp_wishno,0))="","",INDEX(exp_prio,MATCH(45,exp_wishno,0)))) | E51: =IF($A51="","",IF(INDEX(exp_year,MATCH(45,exp_wishno,0))="","",INDEX(exp_year,MATCH(45,exp_wishno,0)))) | F51: =IF($A51="","",IF(INDEX(exp_month,MATCH(45,exp_wishno,0))="","",INDEX(exp_month,MATCH(45,exp_wishno,0)))) | G51: =IF($A51="","",IF(INDEX(exp_plan,MATCH(45,exp_wishno,0))="","",INDEX(exp_plan,MATCH(45,exp_wishno,0)))) | H51: =IF($A51="","",IF(INDEX(exp_fact,MATCH(45,exp_wishno,0))="","",INDEX(exp_fact,MATCH(45,exp_wishno,0)))) | I51: =IF($A51="","",IF(INDEX(exp_status,MATCH(45,exp_wishno,0))="","",INDEX(exp_status,MATCH(45,exp_wishno,0))))
A52: =IF(ISNA(MATCH(46,exp_wishno,0)),"",46) | B52: =IF($A52="","",IF(INDEX(exp_desc,MATCH(46,exp_wishno,0))="","",INDEX(exp_desc,MATCH(46,exp_wishno,0)))) | C52: =IF($A52="","",IF(INDEX(exp_cat,MATCH(46,exp_wishno,0))="","",INDEX(exp_cat,MATCH(46,exp_wishno,0)))) | D52: =IF($A52="","",IF(INDEX(exp_prio,MATCH(46,exp_wishno,0))="","",INDEX(exp_prio,MATCH(46,exp_wishno,0)))) | E52: =IF($A52="","",IF(INDEX(exp_year,MATCH(46,exp_wishno,0))="","",INDEX(exp_year,MATCH(46,exp_wishno,0)))) | F52: =IF($A52="","",IF(INDEX(exp_month,MATCH(46,exp_wishno,0))="","",INDEX(exp_month,MATCH(46,exp_wishno,0)))) | G52: =IF($A52="","",IF(INDEX(exp_plan,MATCH(46,exp_wishno,0))="","",INDEX(exp_plan,MATCH(46,exp_wishno,0)))) | H52: =IF($A52="","",IF(INDEX(exp_fact,MATCH(46,exp_wishno,0))="","",INDEX(exp_fact,MATCH(46,exp_wishno,0)))) | I52: =IF($A52="","",IF(INDEX(exp_status,MATCH(46,exp_wishno,0))="","",INDEX(exp_status,MATCH(46,exp_wishno,0))))
A53: =IF(ISNA(MATCH(47,exp_wishno,0)),"",47) | B53: =IF($A53="","",IF(INDEX(exp_desc,MATCH(47,exp_wishno,0))="","",INDEX(exp_desc,MATCH(47,exp_wishno,0)))) | C53: =IF($A53="","",IF(INDEX(exp_cat,MATCH(47,exp_wishno,0))="","",INDEX(exp_cat,MATCH(47,exp_wishno,0)))) | D53: =IF($A53="","",IF(INDEX(exp_prio,MATCH(47,exp_wishno,0))="","",INDEX(exp_prio,MATCH(47,exp_wishno,0)))) | E53: =IF($A53="","",IF(INDEX(exp_year,MATCH(47,exp_wishno,0))="","",INDEX(exp_year,MATCH(47,exp_wishno,0)))) | F53: =IF($A53="","",IF(INDEX(exp_month,MATCH(47,exp_wishno,0))="","",INDEX(exp_month,MATCH(47,exp_wishno,0)))) | G53: =IF($A53="","",IF(INDEX(exp_plan,MATCH(47,exp_wishno,0))="","",INDEX(exp_plan,MATCH(47,exp_wishno,0)))) | H53: =IF($A53="","",IF(INDEX(exp_fact,MATCH(47,exp_wishno,0))="","",INDEX(exp_fact,MATCH(47,exp_wishno,0)))) | I53: =IF($A53="","",IF(INDEX(exp_status,MATCH(47,exp_wishno,0))="","",INDEX(exp_status,MATCH(47,exp_wishno,0))))
A54: =IF(ISNA(MATCH(48,exp_wishno,0)),"",48) | B54: =IF($A54="","",IF(INDEX(exp_desc,MATCH(48,exp_wishno,0))="","",INDEX(exp_desc,MATCH(48,exp_wishno,0)))) | C54: =IF($A54="","",IF(INDEX(exp_cat,MATCH(48,exp_wishno,0))="","",INDEX(exp_cat,MATCH(48,exp_wishno,0)))) | D54: =IF($A54="","",IF(INDEX(exp_prio,MATCH(48,exp_wishno,0))="","",INDEX(exp_prio,MATCH(48,exp_wishno,0)))) | E54: =IF($A54="","",IF(INDEX(exp_year,MATCH(48,exp_wishno,0))="","",INDEX(exp_year,MATCH(48,exp_wishno,0)))) | F54: =IF($A54="","",IF(INDEX(exp_month,MATCH(48,exp_wishno,0))="","",INDEX(exp_month,MATCH(48,exp_wishno,0)))) | G54: =IF($A54="","",IF(INDEX(exp_plan,MATCH(48,exp_wishno,0))="","",INDEX(exp_plan,MATCH(48,exp_wishno,0)))) | H54: =IF($A54="","",IF(INDEX(exp_fact,MATCH(48,exp_wishno,0))="","",INDEX(exp_fact,MATCH(48,exp_wishno,0)))) | I54: =IF($A54="","",IF(INDEX(exp_status,MATCH(48,exp_wishno,0))="","",INDEX(exp_status,MATCH(48,exp_wishno,0))))
A55: =IF(ISNA(MATCH(49,exp_wishno,0)),"",49) | B55: =IF($A55="","",IF(INDEX(exp_desc,MATCH(49,exp_wishno,0))="","",INDEX(exp_desc,MATCH(49,exp_wishno,0)))) | C55: =IF($A55="","",IF(INDEX(exp_cat,MATCH(49,exp_wishno,0))="","",INDEX(exp_cat,MATCH(49,exp_wishno,0)))) | D55: =IF($A55="","",IF(INDEX(exp_prio,MATCH(49,exp_wishno,0))="","",INDEX(exp_prio,MATCH(49,exp_wishno,0)))) | E55: =IF($A55="","",IF(INDEX(exp_year,MATCH(49,exp_wishno,0))="","",INDEX(exp_year,MATCH(49,exp_wishno,0)))) | F55: =IF($A55="","",IF(INDEX(exp_month,MATCH(49,exp_wishno,0))="","",INDEX(exp_month,MATCH(49,exp_wishno,0)))) | G55: =IF($A55="","",IF(INDEX(exp_plan,MATCH(49,exp_wishno,0))="","",INDEX(exp_plan,MATCH(49,exp_wishno,0)))) | H55: =IF($A55="","",IF(INDEX(exp_fact,MATCH(49,exp_wishno,0))="","",INDEX(exp_fact,MATCH(49,exp_wishno,0)))) | I55: =IF($A55="","",IF(INDEX(exp_status,MATCH(49,exp_wishno,0))="","",INDEX(exp_status,MATCH(49,exp_wishno,0))))
A56: =IF(ISNA(MATCH(50,exp_wishno,0)),"",50) | B56: =IF($A56="","",IF(INDEX(exp_desc,MATCH(50,exp_wishno,0))="","",INDEX(exp_desc,MATCH(50,exp_wishno,0)))) | C56: =IF($A56="","",IF(INDEX(exp_cat,MATCH(50,exp_wishno,0))="","",INDEX(exp_cat,MATCH(50,exp_wishno,0)))) | D56: =IF($A56="","",IF(INDEX(exp_prio,MATCH(50,exp_wishno,0))="","",INDEX(exp_prio,MATCH(50,exp_wishno,0)))) | E56: =IF($A56="","",IF(INDEX(exp_year,MATCH(50,exp_wishno,0))="","",INDEX(exp_year,MATCH(50,exp_wishno,0)))) | F56: =IF($A56="","",IF(INDEX(exp_month,MATCH(50,exp_wishno,0))="","",INDEX(exp_month,MATCH(50,exp_wishno,0)))) | G56: =IF($A56="","",IF(INDEX(exp_plan,MATCH(50,exp_wishno,0))="","",INDEX(exp_plan,MATCH(50,exp_wishno,0)))) | H56: =IF($A56="","",IF(INDEX(exp_fact,MATCH(50,exp_wishno,0))="","",INDEX(exp_fact,MATCH(50,exp_wishno,0)))) | I56: =IF($A56="","",IF(INDEX(exp_status,MATCH(50,exp_wishno,0))="","",INDEX(exp_status,MATCH(50,exp_wishno,0))))
A57: =IF(ISNA(MATCH(51,exp_wishno,0)),"",51) | B57: =IF($A57="","",IF(INDEX(exp_desc,MATCH(51,exp_wishno,0))="","",INDEX(exp_desc,MATCH(51,exp_wishno,0)))) | C57: =IF($A57="","",IF(INDEX(exp_cat,MATCH(51,exp_wishno,0))="","",INDEX(exp_cat,MATCH(51,exp_wishno,0)))) | D57: =IF($A57="","",IF(INDEX(exp_prio,MATCH(51,exp_wishno,0))="","",INDEX(exp_prio,MATCH(51,exp_wishno,0)))) | E57: =IF($A57="","",IF(INDEX(exp_year,MATCH(51,exp_wishno,0))="","",INDEX(exp_year,MATCH(51,exp_wishno,0)))) | F57: =IF($A57="","",IF(INDEX(exp_month,MATCH(51,exp_wishno,0))="","",INDEX(exp_month,MATCH(51,exp_wishno,0)))) | G57: =IF($A57="","",IF(INDEX(exp_plan,MATCH(51,exp_wishno,0))="","",INDEX(exp_plan,MATCH(51,exp_wishno,0)))) | H57: =IF($A57="","",IF(INDEX(exp_fact,MATCH(51,exp_wishno,0))="","",INDEX(exp_fact,MATCH(51,exp_wishno,0)))) | I57: =IF($A57="","",IF(INDEX(exp_status,MATCH(51,exp_wishno,0))="","",INDEX(exp_status,MATCH(51,exp_wishno,0))))
A58: =IF(ISNA(MATCH(52,exp_wishno,0)),"",52) | B58: =IF($A58="","",IF(INDEX(exp_desc,MATCH(52,exp_wishno,0))="","",INDEX(exp_desc,MATCH(52,exp_wishno,0)))) | C58: =IF($A58="","",IF(INDEX(exp_cat,MATCH(52,exp_wishno,0))="","",INDEX(exp_cat,MATCH(52,exp_wishno,0)))) | D58: =IF($A58="","",IF(INDEX(exp_prio,MATCH(52,exp_wishno,0))="","",INDEX(exp_prio,MATCH(52,exp_wishno,0)))) | E58: =IF($A58="","",IF(INDEX(exp_year,MATCH(52,exp_wishno,0))="","",INDEX(exp_year,MATCH(52,exp_wishno,0)))) | F58: =IF($A58="","",IF(INDEX(exp_month,MATCH(52,exp_wishno,0))="","",INDEX(exp_month,MATCH(52,exp_wishno,0)))) | G58: =IF($A58="","",IF(INDEX(exp_plan,MATCH(52,exp_wishno,0))="","",INDEX(exp_plan,MATCH(52,exp_wishno,0)))) | H58: =IF($A58="","",IF(INDEX(exp_fact,MATCH(52,exp_wishno,0))="","",INDEX(exp_fact,MATCH(52,exp_wishno,0)))) | I58: =IF($A58="","",IF(INDEX(exp_status,MATCH(52,exp_wishno,0))="","",INDEX(exp_status,MATCH(52,exp_wishno,0))))
A59: =IF(ISNA(MATCH(53,exp_wishno,0)),"",53) | B59: =IF($A59="","",IF(INDEX(exp_desc,MATCH(53,exp_wishno,0))="","",INDEX(exp_desc,MATCH(53,exp_wishno,0)))) | C59: =IF($A59="","",IF(INDEX(exp_cat,MATCH(53,exp_wishno,0))="","",INDEX(exp_cat,MATCH(53,exp_wishno,0)))) | D59: =IF($A59="","",IF(INDEX(exp_prio,MATCH(53,exp_wishno,0))="","",INDEX(exp_prio,MATCH(53,exp_wishno,0)))) | E59: =IF($A59="","",IF(INDEX(exp_year,MATCH(53,exp_wishno,0))="","",INDEX(exp_year,MATCH(53,exp_wishno,0)))) | F59: =IF($A59="","",IF(INDEX(exp_month,MATCH(53,exp_wishno,0))="","",INDEX(exp_month,MATCH(53,exp_wishno,0)))) | G59: =IF($A59="","",IF(INDEX(exp_plan,MATCH(53,exp_wishno,0))="","",INDEX(exp_plan,MATCH(53,exp_wishno,0)))) | H59: =IF($A59="","",IF(INDEX(exp_fact,MATCH(53,exp_wishno,0))="","",INDEX(exp_fact,MATCH(53,exp_wishno,0)))) | I59: =IF($A59="","",IF(INDEX(exp_status,MATCH(53,exp_wishno,0))="","",INDEX(exp_status,MATCH(53,exp_wishno,0))))
A60: =IF(ISNA(MATCH(54,exp_wishno,0)),"",54) | B60: =IF($A60="","",IF(INDEX(exp_desc,MATCH(54,exp_wishno,0))="","",INDEX(exp_desc,MATCH(54,exp_wishno,0)))) | C60: =IF($A60="","",IF(INDEX(exp_cat,MATCH(54,exp_wishno,0))="","",INDEX(exp_cat,MATCH(54,exp_wishno,0)))) | D60: =IF($A60="","",IF(INDEX(exp_prio,MATCH(54,exp_wishno,0))="","",INDEX(exp_prio,MATCH(54,exp_wishno,0)))) | E60: =IF($A60="","",IF(INDEX(exp_year,MATCH(54,exp_wishno,0))="","",INDEX(exp_year,MATCH(54,exp_wishno,0)))) | F60: =IF($A60="","",IF(INDEX(exp_month,MATCH(54,exp_wishno,0))="","",INDEX(exp_month,MATCH(54,exp_wishno,0)))) | G60: =IF($A60="","",IF(INDEX(exp_plan,MATCH(54,exp_wishno,0))="","",INDEX(exp_plan,MATCH(54,exp_wishno,0)))) | H60: =IF($A60="","",IF(INDEX(exp_fact,MATCH(54,exp_wishno,0))="","",INDEX(exp_fact,MATCH(54,exp_wishno,0)))) | I60: =IF($A60="","",IF(INDEX(exp_status,MATCH(54,exp_wishno,0))="","",INDEX(exp_status,MATCH(54,exp_wishno,0))))
A61: =IF(ISNA(MATCH(55,exp_wishno,0)),"",55) | B61: =IF($A61="","",IF(INDEX(exp_desc,MATCH(55,exp_wishno,0))="","",INDEX(exp_desc,MATCH(55,exp_wishno,0)))) | C61: =IF($A61="","",IF(INDEX(exp_cat,MATCH(55,exp_wishno,0))="","",INDEX(exp_cat,MATCH(55,exp_wishno,0)))) | D61: =IF($A61="","",IF(INDEX(exp_prio,MATCH(55,exp_wishno,0))="","",INDEX(exp_prio,MATCH(55,exp_wishno,0)))) | E61: =IF($A61="","",IF(INDEX(exp_year,MATCH(55,exp_wishno,0))="","",INDEX(exp_year,MATCH(55,exp_wishno,0)))) | F61: =IF($A61="","",IF(INDEX(exp_month,MATCH(55,exp_wishno,0))="","",INDEX(exp_month,MATCH(55,exp_wishno,0)))) | G61: =IF($A61="","",IF(INDEX(exp_plan,MATCH(55,exp_wishno,0))="","",INDEX(exp_plan,MATCH(55,exp_wishno,0)))) | H61: =IF($A61="","",IF(INDEX(exp_fact,MATCH(55,exp_wishno,0))="","",INDEX(exp_fact,MATCH(55,exp_wishno,0)))) | I61: =IF($A61="","",IF(INDEX(exp_status,MATCH(55,exp_wishno,0))="","",INDEX(exp_status,MATCH(55,exp_wishno,0))))
A62: =IF(ISNA(MATCH(56,exp_wishno,0)),"",56) | B62: =IF($A62="","",IF(INDEX(exp_desc,MATCH(56,exp_wishno,0))="","",INDEX(exp_desc,MATCH(56,exp_wishno,0)))) | C62: =IF($A62="","",IF(INDEX(exp_cat,MATCH(56,exp_wishno,0))="","",INDEX(exp_cat,MATCH(56,exp_wishno,0)))) | D62: =IF($A62="","",IF(INDEX(exp_prio,MATCH(56,exp_wishno,0))="","",INDEX(exp_prio,MATCH(56,exp_wishno,0)))) | E62: =IF($A62="","",IF(INDEX(exp_year,MATCH(56,exp_wishno,0))="","",INDEX(exp_year,MATCH(56,exp_wishno,0)))) | F62: =IF($A62="","",IF(INDEX(exp_month,MATCH(56,exp_wishno,0))="","",INDEX(exp_month,MATCH(56,exp_wishno,0)))) | G62: =IF($A62="","",IF(INDEX(exp_plan,MATCH(56,exp_wishno,0))="","",INDEX(exp_plan,MATCH(56,exp_wishno,0)))) | H62: =IF($A62="","",IF(INDEX(exp_fact,MATCH(56,exp_wishno,0))="","",INDEX(exp_fact,MATCH(56,exp_wishno,0)))) | I62: =IF($A62="","",IF(INDEX(exp_status,MATCH(56,exp_wishno,0))="","",INDEX(exp_status,MATCH(56,exp_wishno,0))))
A63: =IF(ISNA(MATCH(57,exp_wishno,0)),"",57) | B63: =IF($A63="","",IF(INDEX(exp_desc,MATCH(57,exp_wishno,0))="","",INDEX(exp_desc,MATCH(57,exp_wishno,0)))) | C63: =IF($A63="","",IF(INDEX(exp_cat,MATCH(57,exp_wishno,0))="","",INDEX(exp_cat,MATCH(57,exp_wishno,0)))) | D63: =IF($A63="","",IF(INDEX(exp_prio,MATCH(57,exp_wishno,0))="","",INDEX(exp_prio,MATCH(57,exp_wishno,0)))) | E63: =IF($A63="","",IF(INDEX(exp_year,MATCH(57,exp_wishno,0))="","",INDEX(exp_year,MATCH(57,exp_wishno,0)))) | F63: =IF($A63="","",IF(INDEX(exp_month,MATCH(57,exp_wishno,0))="","",INDEX(exp_month,MATCH(57,exp_wishno,0)))) | G63: =IF($A63="","",IF(INDEX(exp_plan,MATCH(57,exp_wishno,0))="","",INDEX(exp_plan,MATCH(57,exp_wishno,0)))) | H63: =IF($A63="","",IF(INDEX(exp_fact,MATCH(57,exp_wishno,0))="","",INDEX(exp_fact,MATCH(57,exp_wishno,0)))) | I63: =IF($A63="","",IF(INDEX(exp_status,MATCH(57,exp_wishno,0))="","",INDEX(exp_status,MATCH(57,exp_wishno,0))))
A64: =IF(ISNA(MATCH(58,exp_wishno,0)),"",58) | B64: =IF($A64="","",IF(INDEX(exp_desc,MATCH(58,exp_wishno,0))="","",INDEX(exp_desc,MATCH(58,exp_wishno,0)))) | C64: =IF($A64="","",IF(INDEX(exp_cat,MATCH(58,exp_wishno,0))="","",INDEX(exp_cat,MATCH(58,exp_wishno,0)))) | D64: =IF($A64="","",IF(INDEX(exp_prio,MATCH(58,exp_wishno,0))="","",INDEX(exp_prio,MATCH(58,exp_wishno,0)))) | E64: =IF($A64="","",IF(INDEX(exp_year,MATCH(58,exp_wishno,0))="","",INDEX(exp_year,MATCH(58,exp_wishno,0)))) | F64: =IF($A64="","",IF(INDEX(exp_month,MATCH(58,exp_wishno,0))="","",INDEX(exp_month,MATCH(58,exp_wishno,0)))) | G64: =IF($A64="","",IF(INDEX(exp_plan,MATCH(58,exp_wishno,0))="","",INDEX(exp_plan,MATCH(58,exp_wishno,0)))) | H64: =IF($A64="","",IF(INDEX(exp_fact,MATCH(58,exp_wishno,0))="","",INDEX(exp_fact,MATCH(58,exp_wishno,0)))) | I64: =IF($A64="","",IF(INDEX(exp_status,MATCH(58,exp_wishno,0))="","",INDEX(exp_status,MATCH(58,exp_wishno,0))))
A65: =IF(ISNA(MATCH(59,exp_wishno,0)),"",59) | B65: =IF($A65="","",IF(INDEX(exp_desc,MATCH(59,exp_wishno,0))="","",INDEX(exp_desc,MATCH(59,exp_wishno,0)))) | C65: =IF($A65="","",IF(INDEX(exp_cat,MATCH(59,exp_wishno,0))="","",INDEX(exp_cat,MATCH(59,exp_wishno,0)))) | D65: =IF($A65="","",IF(INDEX(exp_prio,MATCH(59,exp_wishno,0))="","",INDEX(exp_prio,MATCH(59,exp_wishno,0)))) | E65: =IF($A65="","",IF(INDEX(exp_year,MATCH(59,exp_wishno,0))="","",INDEX(exp_year,MATCH(59,exp_wishno,0)))) | F65: =IF($A65="","",IF(INDEX(exp_month,MATCH(59,exp_wishno,0))="","",INDEX(exp_month,MATCH(59,exp_wishno,0)))) | G65: =IF($A65="","",IF(INDEX(exp_plan,MATCH(59,exp_wishno,0))="","",INDEX(exp_plan,MATCH(59,exp_wishno,0)))) | H65: =IF($A65="","",IF(INDEX(exp_fact,MATCH(59,exp_wishno,0))="","",INDEX(exp_fact,MATCH(59,exp_wishno,0)))) | I65: =IF($A65="","",IF(INDEX(exp_status,MATCH(59,exp_wishno,0))="","",INDEX(exp_status,MATCH(59,exp_wishno,0))))
A66: =IF(ISNA(MATCH(60,exp_wishno,0)),"",60) | B66: =IF($A66="","",IF(INDEX(exp_desc,MATCH(60,exp_wishno,0))="","",INDEX(exp_desc,MATCH(60,exp_wishno,0)))) | C66: =IF($A66="","",IF(INDEX(exp_cat,MATCH(60,exp_wishno,0))="","",INDEX(exp_cat,MATCH(60,exp_wishno,0)))) | D66: =IF($A66="","",IF(INDEX(exp_prio,MATCH(60,exp_wishno,0))="","",INDEX(exp_prio,MATCH(60,exp_wishno,0)))) | E66: =IF($A66="","",IF(INDEX(exp_year,MATCH(60,exp_wishno,0))="","",INDEX(exp_year,MATCH(60,exp_wishno,0)))) | F66: =IF($A66="","",IF(INDEX(exp_month,MATCH(60,exp_wishno,0))="","",INDEX(exp_month,MATCH(60,exp_wishno,0)))) | G66: =IF($A66="","",IF(INDEX(exp_plan,MATCH(60,exp_wishno,0))="","",INDEX(exp_plan,MATCH(60,exp_wishno,0)))) | H66: =IF($A66="","",IF(INDEX(exp_fact,MATCH(60,exp_wishno,0))="","",INDEX(exp_fact,MATCH(60,exp_wishno,0)))) | I66: =IF($A66="","",IF(INDEX(exp_status,MATCH(60,exp_wishno,0))="","",INDEX(exp_status,MATCH(60,exp_wishno,0))))
A67: =IF(ISNA(MATCH(61,exp_wishno,0)),"",61) | B67: =IF($A67="","",IF(INDEX(exp_desc,MATCH(61,exp_wishno,0))="","",INDEX(exp_desc,MATCH(61,exp_wishno,0)))) | C67: =IF($A67="","",IF(INDEX(exp_cat,MATCH(61,exp_wishno,0))="","",INDEX(exp_cat,MATCH(61,exp_wishno,0)))) | D67: =IF($A67="","",IF(INDEX(exp_prio,MATCH(61,exp_wishno,0))="","",INDEX(exp_prio,MATCH(61,exp_wishno,0)))) | E67: =IF($A67="","",IF(INDEX(exp_year,MATCH(61,exp_wishno,0))="","",INDEX(exp_year,MATCH(61,exp_wishno,0)))) | F67: =IF($A67="","",IF(INDEX(exp_month,MATCH(61,exp_wishno,0))="","",INDEX(exp_month,MATCH(61,exp_wishno,0)))) | G67: =IF($A67="","",IF(INDEX(exp_plan,MATCH(61,exp_wishno,0))="","",INDEX(exp_plan,MATCH(61,exp_wishno,0)))) | H67: =IF($A67="","",IF(INDEX(exp_fact,MATCH(61,exp_wishno,0))="","",INDEX(exp_fact,MATCH(61,exp_wishno,0)))) | I67: =IF($A67="","",IF(INDEX(exp_status,MATCH(61,exp_wishno,0))="","",INDEX(exp_status,MATCH(61,exp_wishno,0))))
A68: =IF(ISNA(MATCH(62,exp_wishno,0)),"",62) | B68: =IF($A68="","",IF(INDEX(exp_desc,MATCH(62,exp_wishno,0))="","",INDEX(exp_desc,MATCH(62,exp_wishno,0)))) | C68: =IF($A68="","",IF(INDEX(exp_cat,MATCH(62,exp_wishno,0))="","",INDEX(exp_cat,MATCH(62,exp_wishno,0)))) | D68: =IF($A68="","",IF(INDEX(exp_prio,MATCH(62,exp_wishno,0))="","",INDEX(exp_prio,MATCH(62,exp_wishno,0)))) | E68: =IF($A68="","",IF(INDEX(exp_year,MATCH(62,exp_wishno,0))="","",INDEX(exp_year,MATCH(62,exp_wishno,0)))) | F68: =IF($A68="","",IF(INDEX(exp_month,MATCH(62,exp_wishno,0))="","",INDEX(exp_month,MATCH(62,exp_wishno,0)))) | G68: =IF($A68="","",IF(INDEX(exp_plan,MATCH(62,exp_wishno,0))="","",INDEX(exp_plan,MATCH(62,exp_wishno,0)))) | H68: =IF($A68="","",IF(INDEX(exp_fact,MATCH(62,exp_wishno,0))="","",INDEX(exp_fact,MATCH(62,exp_wishno,0)))) | I68: =IF($A68="","",IF(INDEX(exp_status,MATCH(62,exp_wishno,0))="","",INDEX(exp_status,MATCH(62,exp_wishno,0))))
A69: =IF(ISNA(MATCH(63,exp_wishno,0)),"",63) | B69: =IF($A69="","",IF(INDEX(exp_desc,MATCH(63,exp_wishno,0))="","",INDEX(exp_desc,MATCH(63,exp_wishno,0)))) | C69: =IF($A69="","",IF(INDEX(exp_cat,MATCH(63,exp_wishno,0))="","",INDEX(exp_cat,MATCH(63,exp_wishno,0)))) | D69: =IF($A69="","",IF(INDEX(exp_prio,MATCH(63,exp_wishno,0))="","",INDEX(exp_prio,MATCH(63,exp_wishno,0)))) | E69: =IF($A69="","",IF(INDEX(exp_year,MATCH(63,exp_wishno,0))="","",INDEX(exp_year,MATCH(63,exp_wishno,0)))) | F69: =IF($A69="","",IF(INDEX(exp_month,MATCH(63,exp_wishno,0))="","",INDEX(exp_month,MATCH(63,exp_wishno,0)))) | G69: =IF($A69="","",IF(INDEX(exp_plan,MATCH(63,exp_wishno,0))="","",INDEX(exp_plan,MATCH(63,exp_wishno,0)))) | H69: =IF($A69="","",IF(INDEX(exp_fact,MATCH(63,exp_wishno,0))="","",INDEX(exp_fact,MATCH(63,exp_wishno,0)))) | I69: =IF($A69="","",IF(INDEX(exp_status,MATCH(63,exp_wishno,0))="","",INDEX(exp_status,MATCH(63,exp_wishno,0))))
A70: =IF(ISNA(MATCH(64,exp_wishno,0)),"",64) | B70: =IF($A70="","",IF(INDEX(exp_desc,MATCH(64,exp_wishno,0))="","",INDEX(exp_desc,MATCH(64,exp_wishno,0)))) | C70: =IF($A70="","",IF(INDEX(exp_cat,MATCH(64,exp_wishno,0))="","",INDEX(exp_cat,MATCH(64,exp_wishno,0)))) | D70: =IF($A70="","",IF(INDEX(exp_prio,MATCH(64,exp_wishno,0))="","",INDEX(exp_prio,MATCH(64,exp_wishno,0)))) | E70: =IF($A70="","",IF(INDEX(exp_year,MATCH(64,exp_wishno,0))="","",INDEX(exp_year,MATCH(64,exp_wishno,0)))) | F70: =IF($A70="","",IF(INDEX(exp_month,MATCH(64,exp_wishno,0))="","",INDEX(exp_month,MATCH(64,exp_wishno,0)))) | G70: =IF($A70="","",IF(INDEX(exp_plan,MATCH(64,exp_wishno,0))="","",INDEX(exp_plan,MATCH(64,exp_wishno,0)))) | H70: =IF($A70="","",IF(INDEX(exp_fact,MATCH(64,exp_wishno,0))="","",INDEX(exp_fact,MATCH(64,exp_wishno,0)))) | I70: =IF($A70="","",IF(INDEX(exp_status,MATCH(64,exp_wishno,0))="","",INDEX(exp_status,MATCH(64,exp_wishno,0))))
A71: =IF(ISNA(MATCH(65,exp_wishno,0)),"",65) | B71: =IF($A71="","",IF(INDEX(exp_desc,MATCH(65,exp_wishno,0))="","",INDEX(exp_desc,MATCH(65,exp_wishno,0)))) | C71: =IF($A71="","",IF(INDEX(exp_cat,MATCH(65,exp_wishno,0))="","",INDEX(exp_cat,MATCH(65,exp_wishno,0)))) | D71: =IF($A71="","",IF(INDEX(exp_prio,MATCH(65,exp_wishno,0))="","",INDEX(exp_prio,MATCH(65,exp_wishno,0)))) | E71: =IF($A71="","",IF(INDEX(exp_year,MATCH(65,exp_wishno,0))="","",INDEX(exp_year,MATCH(65,exp_wishno,0)))) | F71: =IF($A71="","",IF(INDEX(exp_month,MATCH(65,exp_wishno,0))="","",INDEX(exp_month,MATCH(65,exp_wishno,0)))) | G71: =IF($A71="","",IF(INDEX(exp_plan,MATCH(65,exp_wishno,0))="","",INDEX(exp_plan,MATCH(65,exp_wishno,0)))) | H71: =IF($A71="","",IF(INDEX(exp_fact,MATCH(65,exp_wishno,0))="","",INDEX(exp_fact,MATCH(65,exp_wishno,0)))) | I71: =IF($A71="","",IF(INDEX(exp_status,MATCH(65,exp_wishno,0))="","",INDEX(exp_status,MATCH(65,exp_wishno,0))))
A72: =IF(ISNA(MATCH(66,exp_wishno,0)),"",66) | B72: =IF($A72="","",IF(INDEX(exp_desc,MATCH(66,exp_wishno,0))="","",INDEX(exp_desc,MATCH(66,exp_wishno,0)))) | C72: =IF($A72="","",IF(INDEX(exp_cat,MATCH(66,exp_wishno,0))="","",INDEX(exp_cat,MATCH(66,exp_wishno,0)))) | D72: =IF($A72="","",IF(INDEX(exp_prio,MATCH(66,exp_wishno,0))="","",INDEX(exp_prio,MATCH(66,exp_wishno,0)))) | E72: =IF($A72="","",IF(INDEX(exp_year,MATCH(66,exp_wishno,0))="","",INDEX(exp_year,MATCH(66,exp_wishno,0)))) | F72: =IF($A72="","",IF(INDEX(exp_month,MATCH(66,exp_wishno,0))="","",INDEX(exp_month,MATCH(66,exp_wishno,0)))) | G72: =IF($A72="","",IF(INDEX(exp_plan,MATCH(66,exp_wishno,0))="","",INDEX(exp_plan,MATCH(66,exp_wishno,0)))) | H72: =IF($A72="","",IF(INDEX(exp_fact,MATCH(66,exp_wishno,0))="","",INDEX(exp_fact,MATCH(66,exp_wishno,0)))) | I72: =IF($A72="","",IF(INDEX(exp_status,MATCH(66,exp_wishno,0))="","",INDEX(exp_status,MATCH(66,exp_wishno,0))))
A73: =IF(ISNA(MATCH(67,exp_wishno,0)),"",67) | B73: =IF($A73="","",IF(INDEX(exp_desc,MATCH(67,exp_wishno,0))="","",INDEX(exp_desc,MATCH(67,exp_wishno,0)))) | C73: =IF($A73="","",IF(INDEX(exp_cat,MATCH(67,exp_wishno,0))="","",INDEX(exp_cat,MATCH(67,exp_wishno,0)))) | D73: =IF($A73="","",IF(INDEX(exp_prio,MATCH(67,exp_wishno,0))="","",INDEX(exp_prio,MATCH(67,exp_wishno,0)))) | E73: =IF($A73="","",IF(INDEX(exp_year,MATCH(67,exp_wishno,0))="","",INDEX(exp_year,MATCH(67,exp_wishno,0)))) | F73: =IF($A73="","",IF(INDEX(exp_month,MATCH(67,exp_wishno,0))="","",INDEX(exp_month,MATCH(67,exp_wishno,0)))) | G73: =IF($A73="","",IF(INDEX(exp_plan,MATCH(67,exp_wishno,0))="","",INDEX(exp_plan,MATCH(67,exp_wishno,0)))) | H73: =IF($A73="","",IF(INDEX(exp_fact,MATCH(67,exp_wishno,0))="","",INDEX(exp_fact,MATCH(67,exp_wishno,0)))) | I73: =IF($A73="","",IF(INDEX(exp_status,MATCH(67,exp_wishno,0))="","",INDEX(exp_status,MATCH(67,exp_wishno,0))))
A74: =IF(ISNA(MATCH(68,exp_wishno,0)),"",68) | B74: =IF($A74="","",IF(INDEX(exp_desc,MATCH(68,exp_wishno,0))="","",INDEX(exp_desc,MATCH(68,exp_wishno,0)))) | C74: =IF($A74="","",IF(INDEX(exp_cat,MATCH(68,exp_wishno,0))="","",INDEX(exp_cat,MATCH(68,exp_wishno,0)))) | D74: =IF($A74="","",IF(INDEX(exp_prio,MATCH(68,exp_wishno,0))="","",INDEX(exp_prio,MATCH(68,exp_wishno,0)))) | E74: =IF($A74="","",IF(INDEX(exp_year,MATCH(68,exp_wishno,0))="","",INDEX(exp_year,MATCH(68,exp_wishno,0)))) | F74: =IF($A74="","",IF(INDEX(exp_month,MATCH(68,exp_wishno,0))="","",INDEX(exp_month,MATCH(68,exp_wishno,0)))) | G74: =IF($A74="","",IF(INDEX(exp_plan,MATCH(68,exp_wishno,0))="","",INDEX(exp_plan,MATCH(68,exp_wishno,0)))) | H74: =IF($A74="","",IF(INDEX(exp_fact,MATCH(68,exp_wishno,0))="","",INDEX(exp_fact,MATCH(68,exp_wishno,0)))) | I74: =IF($A74="","",IF(INDEX(exp_status,MATCH(68,exp_wishno,0))="","",INDEX(exp_status,MATCH(68,exp_wishno,0))))
A75: =IF(ISNA(MATCH(69,exp_wishno,0)),"",69) | B75: =IF($A75="","",IF(INDEX(exp_desc,MATCH(69,exp_wishno,0))="","",INDEX(exp_desc,MATCH(69,exp_wishno,0)))) | C75: =IF($A75="","",IF(INDEX(exp_cat,MATCH(69,exp_wishno,0))="","",INDEX(exp_cat,MATCH(69,exp_wishno,0)))) | D75: =IF($A75="","",IF(INDEX(exp_prio,MATCH(69,exp_wishno,0))="","",INDEX(exp_prio,MATCH(69,exp_wishno,0)))) | E75: =IF($A75="","",IF(INDEX(exp_year,MATCH(69,exp_wishno,0))="","",INDEX(exp_year,MATCH(69,exp_wishno,0)))) | F75: =IF($A75="","",IF(INDEX(exp_month,MATCH(69,exp_wishno,0))="","",INDEX(exp_month,MATCH(69,exp_wishno,0)))) | G75: =IF($A75="","",IF(INDEX(exp_plan,MATCH(69,exp_wishno,0))="","",INDEX(exp_plan,MATCH(69,exp_wishno,0)))) | H75: =IF($A75="","",IF(INDEX(exp_fact,MATCH(69,exp_wishno,0))="","",INDEX(exp_fact,MATCH(69,exp_wishno,0)))) | I75: =IF($A75="","",IF(INDEX(exp_status,MATCH(69,exp_wishno,0))="","",INDEX(exp_status,MATCH(69,exp_wishno,0))))
A76: =IF(ISNA(MATCH(70,exp_wishno,0)),"",70) | B76: =IF($A76="","",IF(INDEX(exp_desc,MATCH(70,exp_wishno,0))="","",INDEX(exp_desc,MATCH(70,exp_wishno,0)))) | C76: =IF($A76="","",IF(INDEX(exp_cat,MATCH(70,exp_wishno,0))="","",INDEX(exp_cat,MATCH(70,exp_wishno,0)))) | D76: =IF($A76="","",IF(INDEX(exp_prio,MATCH(70,exp_wishno,0))="","",INDEX(exp_prio,MATCH(70,exp_wishno,0)))) | E76: =IF($A76="","",IF(INDEX(exp_year,MATCH(70,exp_wishno,0))="","",INDEX(exp_year,MATCH(70,exp_wishno,0)))) | F76: =IF($A76="","",IF(INDEX(exp_month,MATCH(70,exp_wishno,0))="","",INDEX(exp_month,MATCH(70,exp_wishno,0)))) | G76: =IF($A76="","",IF(INDEX(exp_plan,MATCH(70,exp_wishno,0))="","",INDEX(exp_plan,MATCH(70,exp_wishno,0)))) | H76: =IF($A76="","",IF(INDEX(exp_fact,MATCH(70,exp_wishno,0))="","",INDEX(exp_fact,MATCH(70,exp_wishno,0)))) | I76: =IF($A76="","",IF(INDEX(exp_status,MATCH(70,exp_wishno,0))="","",INDEX(exp_status,MATCH(70,exp_wishno,0))))
A77: =IF(ISNA(MATCH(71,exp_wishno,0)),"",71) | B77: =IF($A77="","",IF(INDEX(exp_desc,MATCH(71,exp_wishno,0))="","",INDEX(exp_desc,MATCH(71,exp_wishno,0)))) | C77: =IF($A77="","",IF(INDEX(exp_cat,MATCH(71,exp_wishno,0))="","",INDEX(exp_cat,MATCH(71,exp_wishno,0)))) | D77: =IF($A77="","",IF(INDEX(exp_prio,MATCH(71,exp_wishno,0))="","",INDEX(exp_prio,MATCH(71,exp_wishno,0)))) | E77: =IF($A77="","",IF(INDEX(exp_year,MATCH(71,exp_wishno,0))="","",INDEX(exp_year,MATCH(71,exp_wishno,0)))) | F77: =IF($A77="","",IF(INDEX(exp_month,MATCH(71,exp_wishno,0))="","",INDEX(exp_month,MATCH(71,exp_wishno,0)))) | G77: =IF($A77="","",IF(INDEX(exp_plan,MATCH(71,exp_wishno,0))="","",INDEX(exp_plan,MATCH(71,exp_wishno,0)))) | H77: =IF($A77="","",IF(INDEX(exp_fact,MATCH(71,exp_wishno,0))="","",INDEX(exp_fact,MATCH(71,exp_wishno,0)))) | I77: =IF($A77="","",IF(INDEX(exp_status,MATCH(71,exp_wishno,0))="","",INDEX(exp_status,MATCH(71,exp_wishno,0))))
A78: =IF(ISNA(MATCH(72,exp_wishno,0)),"",72) | B78: =IF($A78="","",IF(INDEX(exp_desc,MATCH(72,exp_wishno,0))="","",INDEX(exp_desc,MATCH(72,exp_wishno,0)))) | C78: =IF($A78="","",IF(INDEX(exp_cat,MATCH(72,exp_wishno,0))="","",INDEX(exp_cat,MATCH(72,exp_wishno,0)))) | D78: =IF($A78="","",IF(INDEX(exp_prio,MATCH(72,exp_wishno,0))="","",INDEX(exp_prio,MATCH(72,exp_wishno,0)))) | E78: =IF($A78="","",IF(INDEX(exp_year,MATCH(72,exp_wishno,0))="","",INDEX(exp_year,MATCH(72,exp_wishno,0)))) | F78: =IF($A78="","",IF(INDEX(exp_month,MATCH(72,exp_wishno,0))="","",INDEX(exp_month,MATCH(72,exp_wishno,0)))) | G78: =IF($A78="","",IF(INDEX(exp_plan,MATCH(72,exp_wishno,0))="","",INDEX(exp_plan,MATCH(72,exp_wishno,0)))) | H78: =IF($A78="","",IF(INDEX(exp_fact,MATCH(72,exp_wishno,0))="","",INDEX(exp_fact,MATCH(72,exp_wishno,0)))) | I78: =IF($A78="","",IF(INDEX(exp_status,MATCH(72,exp_wishno,0))="","",INDEX(exp_status,MATCH(72,exp_wishno,0))))
A79: =IF(ISNA(MATCH(73,exp_wishno,0)),"",73) | B79: =IF($A79="","",IF(INDEX(exp_desc,MATCH(73,exp_wishno,0))="","",INDEX(exp_desc,MATCH(73,exp_wishno,0)))) | C79: =IF($A79="","",IF(INDEX(exp_cat,MATCH(73,exp_wishno,0))="","",INDEX(exp_cat,MATCH(73,exp_wishno,0)))) | D79: =IF($A79="","",IF(INDEX(exp_prio,MATCH(73,exp_wishno,0))="","",INDEX(exp_prio,MATCH(73,exp_wishno,0)))) | E79: =IF($A79="","",IF(INDEX(exp_year,MATCH(73,exp_wishno,0))="","",INDEX(exp_year,MATCH(73,exp_wishno,0)))) | F79: =IF($A79="","",IF(INDEX(exp_month,MATCH(73,exp_wishno,0))="","",INDEX(exp_month,MATCH(73,exp_wishno,0)))) | G79: =IF($A79="","",IF(INDEX(exp_plan,MATCH(73,exp_wishno,0))="","",INDEX(exp_plan,MATCH(73,exp_wishno,0)))) | H79: =IF($A79="","",IF(INDEX(exp_fact,MATCH(73,exp_wishno,0))="","",INDEX(exp_fact,MATCH(73,exp_wishno,0)))) | I79: =IF($A79="","",IF(INDEX(exp_status,MATCH(73,exp_wishno,0))="","",INDEX(exp_status,MATCH(73,exp_wishno,0))))
A80: =IF(ISNA(MATCH(74,exp_wishno,0)),"",74) | B80: =IF($A80="","",IF(INDEX(exp_desc,MATCH(74,exp_wishno,0))="","",INDEX(exp_desc,MATCH(74,exp_wishno,0)))) | C80: =IF($A80="","",IF(INDEX(exp_cat,MATCH(74,exp_wishno,0))="","",INDEX(exp_cat,MATCH(74,exp_wishno,0)))) | D80: =IF($A80="","",IF(INDEX(exp_prio,MATCH(74,exp_wishno,0))="","",INDEX(exp_prio,MATCH(74,exp_wishno,0)))) | E80: =IF($A80="","",IF(INDEX(exp_year,MATCH(74,exp_wishno,0))="","",INDEX(exp_year,MATCH(74,exp_wishno,0)))) | F80: =IF($A80="","",IF(INDEX(exp_month,MATCH(74,exp_wishno,0))="","",INDEX(exp_month,MATCH(74,exp_wishno,0)))) | G80: =IF($A80="","",IF(INDEX(exp_plan,MATCH(74,exp_wishno,0))="","",INDEX(exp_plan,MATCH(74,exp_wishno,0)))) | H80: =IF($A80="","",IF(INDEX(exp_fact,MATCH(74,exp_wishno,0))="","",INDEX(exp_fact,MATCH(74,exp_wishno,0)))) | I80: =IF($A80="","",IF(INDEX(exp_status,MATCH(74,exp_wishno,0))="","",INDEX(exp_status,MATCH(74,exp_wishno,0))))
A81: =IF(ISNA(MATCH(75,exp_wishno,0)),"",75) | B81: =IF($A81="","",IF(INDEX(exp_desc,MATCH(75,exp_wishno,0))="","",INDEX(exp_desc,MATCH(75,exp_wishno,0)))) | C81: =IF($A81="","",IF(INDEX(exp_cat,MATCH(75,exp_wishno,0))="","",INDEX(exp_cat,MATCH(75,exp_wishno,0)))) | D81: =IF($A81="","",IF(INDEX(exp_prio,MATCH(75,exp_wishno,0))="","",INDEX(exp_prio,MATCH(75,exp_wishno,0)))) | E81: =IF($A81="","",IF(INDEX(exp_year,MATCH(75,exp_wishno,0))="","",INDEX(exp_year,MATCH(75,exp_wishno,0)))) | F81: =IF($A81="","",IF(INDEX(exp_month,MATCH(75,exp_wishno,0))="","",INDEX(exp_month,MATCH(75,exp_wishno,0)))) | G81: =IF($A81="","",IF(INDEX(exp_plan,MATCH(75,exp_wishno,0))="","",INDEX(exp_plan,MATCH(75,exp_wishno,0)))) | H81: =IF($A81="","",IF(INDEX(exp_fact,MATCH(75,exp_wishno,0))="","",INDEX(exp_fact,MATCH(75,exp_wishno,0)))) | I81: =IF($A81="","",IF(INDEX(exp_status,MATCH(75,exp_wishno,0))="","",INDEX(exp_status,MATCH(75,exp_wishno,0))))
A82: =IF(ISNA(MATCH(76,exp_wishno,0)),"",76) | B82: =IF($A82="","",IF(INDEX(exp_desc,MATCH(76,exp_wishno,0))="","",INDEX(exp_desc,MATCH(76,exp_wishno,0)))) | C82: =IF($A82="","",IF(INDEX(exp_cat,MATCH(76,exp_wishno,0))="","",INDEX(exp_cat,MATCH(76,exp_wishno,0)))) | D82: =IF($A82="","",IF(INDEX(exp_prio,MATCH(76,exp_wishno,0))="","",INDEX(exp_prio,MATCH(76,exp_wishno,0)))) | E82: =IF($A82="","",IF(INDEX(exp_year,MATCH(76,exp_wishno,0))="","",INDEX(exp_year,MATCH(76,exp_wishno,0)))) | F82: =IF($A82="","",IF(INDEX(exp_month,MATCH(76,exp_wishno,0))="","",INDEX(exp_month,MATCH(76,exp_wishno,0)))) | G82: =IF($A82="","",IF(INDEX(exp_plan,MATCH(76,exp_wishno,0))="","",INDEX(exp_plan,MATCH(76,exp_wishno,0)))) | H82: =IF($A82="","",IF(INDEX(exp_fact,MATCH(76,exp_wishno,0))="","",INDEX(exp_fact,MATCH(76,exp_wishno,0)))) | I82: =IF($A82="","",IF(INDEX(exp_status,MATCH(76,exp_wishno,0))="","",INDEX(exp_status,MATCH(76,exp_wishno,0))))
A83: =IF(ISNA(MATCH(77,exp_wishno,0)),"",77) | B83: =IF($A83="","",IF(INDEX(exp_desc,MATCH(77,exp_wishno,0))="","",INDEX(exp_desc,MATCH(77,exp_wishno,0)))) | C83: =IF($A83="","",IF(INDEX(exp_cat,MATCH(77,exp_wishno,0))="","",INDEX(exp_cat,MATCH(77,exp_wishno,0)))) | D83: =IF($A83="","",IF(INDEX(exp_prio,MATCH(77,exp_wishno,0))="","",INDEX(exp_prio,MATCH(77,exp_wishno,0)))) | E83: =IF($A83="","",IF(INDEX(exp_year,MATCH(77,exp_wishno,0))="","",INDEX(exp_year,MATCH(77,exp_wishno,0)))) | F83: =IF($A83="","",IF(INDEX(exp_month,MATCH(77,exp_wishno,0))="","",INDEX(exp_month,MATCH(77,exp_wishno,0)))) | G83: =IF($A83="","",IF(INDEX(exp_plan,MATCH(77,exp_wishno,0))="","",INDEX(exp_plan,MATCH(77,exp_wishno,0)))) | H83: =IF($A83="","",IF(INDEX(exp_fact,MATCH(77,exp_wishno,0))="","",INDEX(exp_fact,MATCH(77,exp_wishno,0)))) | I83: =IF($A83="","",IF(INDEX(exp_status,MATCH(77,exp_wishno,0))="","",INDEX(exp_status,MATCH(77,exp_wishno,0))))
A84: =IF(ISNA(MATCH(78,exp_wishno,0)),"",78) | B84: =IF($A84="","",IF(INDEX(exp_desc,MATCH(78,exp_wishno,0))="","",INDEX(exp_desc,MATCH(78,exp_wishno,0)))) | C84: =IF($A84="","",IF(INDEX(exp_cat,MATCH(78,exp_wishno,0))="","",INDEX(exp_cat,MATCH(78,exp_wishno,0)))) | D84: =IF($A84="","",IF(INDEX(exp_prio,MATCH(78,exp_wishno,0))="","",INDEX(exp_prio,MATCH(78,exp_wishno,0)))) | E84: =IF($A84="","",IF(INDEX(exp_year,MATCH(78,exp_wishno,0))="","",INDEX(exp_year,MATCH(78,exp_wishno,0)))) | F84: =IF($A84="","",IF(INDEX(exp_month,MATCH(78,exp_wishno,0))="","",INDEX(exp_month,MATCH(78,exp_wishno,0)))) | G84: =IF($A84="","",IF(INDEX(exp_plan,MATCH(78,exp_wishno,0))="","",INDEX(exp_plan,MATCH(78,exp_wishno,0)))) | H84: =IF($A84="","",IF(INDEX(exp_fact,MATCH(78,exp_wishno,0))="","",INDEX(exp_fact,MATCH(78,exp_wishno,0)))) | I84: =IF($A84="","",IF(INDEX(exp_status,MATCH(78,exp_wishno,0))="","",INDEX(exp_status,MATCH(78,exp_wishno,0))))
A85: =IF(ISNA(MATCH(79,exp_wishno,0)),"",79) | B85: =IF($A85="","",IF(INDEX(exp_desc,MATCH(79,exp_wishno,0))="","",INDEX(exp_desc,MATCH(79,exp_wishno,0)))) | C85: =IF($A85="","",IF(INDEX(exp_cat,MATCH(79,exp_wishno,0))="","",INDEX(exp_cat,MATCH(79,exp_wishno,0)))) | D85: =IF($A85="","",IF(INDEX(exp_prio,MATCH(79,exp_wishno,0))="","",INDEX(exp_prio,MATCH(79,exp_wishno,0)))) | E85: =IF($A85="","",IF(INDEX(exp_year,MATCH(79,exp_wishno,0))="","",INDEX(exp_year,MATCH(79,exp_wishno,0)))) | F85: =IF($A85="","",IF(INDEX(exp_month,MATCH(79,exp_wishno,0))="","",INDEX(exp_month,MATCH(79,exp_wishno,0)))) | G85: =IF($A85="","",IF(INDEX(exp_plan,MATCH(79,exp_wishno,0))="","",INDEX(exp_plan,MATCH(79,exp_wishno,0)))) | H85: =IF($A85="","",IF(INDEX(exp_fact,MATCH(79,exp_wishno,0))="","",INDEX(exp_fact,MATCH(79,exp_wishno,0)))) | I85: =IF($A85="","",IF(INDEX(exp_status,MATCH(79,exp_wishno,0))="","",INDEX(exp_status,MATCH(79,exp_wishno,0))))
A86: =IF(ISNA(MATCH(80,exp_wishno,0)),"",80) | B86: =IF($A86="","",IF(INDEX(exp_desc,MATCH(80,exp_wishno,0))="","",INDEX(exp_desc,MATCH(80,exp_wishno,0)))) | C86: =IF($A86="","",IF(INDEX(exp_cat,MATCH(80,exp_wishno,0))="","",INDEX(exp_cat,MATCH(80,exp_wishno,0)))) | D86: =IF($A86="","",IF(INDEX(exp_prio,MATCH(80,exp_wishno,0))="","",INDEX(exp_prio,MATCH(80,exp_wishno,0)))) | E86: =IF($A86="","",IF(INDEX(exp_year,MATCH(80,exp_wishno,0))="","",INDEX(exp_year,MATCH(80,exp_wishno,0)))) | F86: =IF($A86="","",IF(INDEX(exp_month,MATCH(80,exp_wishno,0))="","",INDEX(exp_month,MATCH(80,exp_wishno,0)))) | G86: =IF($A86="","",IF(INDEX(exp_plan,MATCH(80,exp_wishno,0))="","",INDEX(exp_plan,MATCH(80,exp_wishno,0)))) | H86: =IF($A86="","",IF(INDEX(exp_fact,MATCH(80,exp_wishno,0))="","",INDEX(exp_fact,MATCH(80,exp_wishno,0)))) | I86: =IF($A86="","",IF(INDEX(exp_status,MATCH(80,exp_wishno,0))="","",INDEX(exp_status,MATCH(80,exp_wishno,0))))
A87: =IF(ISNA(MATCH(81,exp_wishno,0)),"",81) | B87: =IF($A87="","",IF(INDEX(exp_desc,MATCH(81,exp_wishno,0))="","",INDEX(exp_desc,MATCH(81,exp_wishno,0)))) | C87: =IF($A87="","",IF(INDEX(exp_cat,MATCH(81,exp_wishno,0))="","",INDEX(exp_cat,MATCH(81,exp_wishno,0)))) | D87: =IF($A87="","",IF(INDEX(exp_prio,MATCH(81,exp_wishno,0))="","",INDEX(exp_prio,MATCH(81,exp_wishno,0)))) | E87: =IF($A87="","",IF(INDEX(exp_year,MATCH(81,exp_wishno,0))="","",INDEX(exp_year,MATCH(81,exp_wishno,0)))) | F87: =IF($A87="","",IF(INDEX(exp_month,MATCH(81,exp_wishno,0))="","",INDEX(exp_month,MATCH(81,exp_wishno,0)))) | G87: =IF($A87="","",IF(INDEX(exp_plan,MATCH(81,exp_wishno,0))="","",INDEX(exp_plan,MATCH(81,exp_wishno,0)))) | H87: =IF($A87="","",IF(INDEX(exp_fact,MATCH(81,exp_wishno,0))="","",INDEX(exp_fact,MATCH(81,exp_wishno,0)))) | I87: =IF($A87="","",IF(INDEX(exp_status,MATCH(81,exp_wishno,0))="","",INDEX(exp_status,MATCH(81,exp_wishno,0))))
A88: =IF(ISNA(MATCH(82,exp_wishno,0)),"",82) | B88: =IF($A88="","",IF(INDEX(exp_desc,MATCH(82,exp_wishno,0))="","",INDEX(exp_desc,MATCH(82,exp_wishno,0)))) | C88: =IF($A88="","",IF(INDEX(exp_cat,MATCH(82,exp_wishno,0))="","",INDEX(exp_cat,MATCH(82,exp_wishno,0)))) | D88: =IF($A88="","",IF(INDEX(exp_prio,MATCH(82,exp_wishno,0))="","",INDEX(exp_prio,MATCH(82,exp_wishno,0)))) | E88: =IF($A88="","",IF(INDEX(exp_year,MATCH(82,exp_wishno,0))="","",INDEX(exp_year,MATCH(82,exp_wishno,0)))) | F88: =IF($A88="","",IF(INDEX(exp_month,MATCH(82,exp_wishno,0))="","",INDEX(exp_month,MATCH(82,exp_wishno,0)))) | G88: =IF($A88="","",IF(INDEX(exp_plan,MATCH(82,exp_wishno,0))="","",INDEX(exp_plan,MATCH(82,exp_wishno,0)))) | H88: =IF($A88="","",IF(INDEX(exp_fact,MATCH(82,exp_wishno,0))="","",INDEX(exp_fact,MATCH(82,exp_wishno,0)))) | I88: =IF($A88="","",IF(INDEX(exp_status,MATCH(82,exp_wishno,0))="","",INDEX(exp_status,MATCH(82,exp_wishno,0))))
A89: =IF(ISNA(MATCH(83,exp_wishno,0)),"",83) | B89: =IF($A89="","",IF(INDEX(exp_desc,MATCH(83,exp_wishno,0))="","",INDEX(exp_desc,MATCH(83,exp_wishno,0)))) | C89: =IF($A89="","",IF(INDEX(exp_cat,MATCH(83,exp_wishno,0))="","",INDEX(exp_cat,MATCH(83,exp_wishno,0)))) | D89: =IF($A89="","",IF(INDEX(exp_prio,MATCH(83,exp_wishno,0))="","",INDEX(exp_prio,MATCH(83,exp_wishno,0)))) | E89: =IF($A89="","",IF(INDEX(exp_year,MATCH(83,exp_wishno,0))="","",INDEX(exp_year,MATCH(83,exp_wishno,0)))) | F89: =IF($A89="","",IF(INDEX(exp_month,MATCH(83,exp_wishno,0))="","",INDEX(exp_month,MATCH(83,exp_wishno,0)))) | G89: =IF($A89="","",IF(INDEX(exp_plan,MATCH(83,exp_wishno,0))="","",INDEX(exp_plan,MATCH(83,exp_wishno,0)))) | H89: =IF($A89="","",IF(INDEX(exp_fact,MATCH(83,exp_wishno,0))="","",INDEX(exp_fact,MATCH(83,exp_wishno,0)))) | I89: =IF($A89="","",IF(INDEX(exp_status,MATCH(83,exp_wishno,0))="","",INDEX(exp_status,MATCH(83,exp_wishno,0))))
A90: =IF(ISNA(MATCH(84,exp_wishno,0)),"",84) | B90: =IF($A90="","",IF(INDEX(exp_desc,MATCH(84,exp_wishno,0))="","",INDEX(exp_desc,MATCH(84,exp_wishno,0)))) | C90: =IF($A90="","",IF(INDEX(exp_cat,MATCH(84,exp_wishno,0))="","",INDEX(exp_cat,MATCH(84,exp_wishno,0)))) | D90: =IF($A90="","",IF(INDEX(exp_prio,MATCH(84,exp_wishno,0))="","",INDEX(exp_prio,MATCH(84,exp_wishno,0)))) | E90: =IF($A90="","",IF(INDEX(exp_year,MATCH(84,exp_wishno,0))="","",INDEX(exp_year,MATCH(84,exp_wishno,0)))) | F90: =IF($A90="","",IF(INDEX(exp_month,MATCH(84,exp_wishno,0))="","",INDEX(exp_month,MATCH(84,exp_wishno,0)))) | G90: =IF($A90="","",IF(INDEX(exp_plan,MATCH(84,exp_wishno,0))="","",INDEX(exp_plan,MATCH(84,exp_wishno,0)))) | H90: =IF($A90="","",IF(INDEX(exp_fact,MATCH(84,exp_wishno,0))="","",INDEX(exp_fact,MATCH(84,exp_wishno,0)))) | I90: =IF($A90="","",IF(INDEX(exp_status,MATCH(84,exp_wishno,0))="","",INDEX(exp_status,MATCH(84,exp_wishno,0))))
A91: =IF(ISNA(MATCH(85,exp_wishno,0)),"",85) | B91: =IF($A91="","",IF(INDEX(exp_desc,MATCH(85,exp_wishno,0))="","",INDEX(exp_desc,MATCH(85,exp_wishno,0)))) | C91: =IF($A91="","",IF(INDEX(exp_cat,MATCH(85,exp_wishno,0))="","",INDEX(exp_cat,MATCH(85,exp_wishno,0)))) | D91: =IF($A91="","",IF(INDEX(exp_prio,MATCH(85,exp_wishno,0))="","",INDEX(exp_prio,MATCH(85,exp_wishno,0)))) | E91: =IF($A91="","",IF(INDEX(exp_year,MATCH(85,exp_wishno,0))="","",INDEX(exp_year,MATCH(85,exp_wishno,0)))) | F91: =IF($A91="","",IF(INDEX(exp_month,MATCH(85,exp_wishno,0))="","",INDEX(exp_month,MATCH(85,exp_wishno,0)))) | G91: =IF($A91="","",IF(INDEX(exp_plan,MATCH(85,exp_wishno,0))="","",INDEX(exp_plan,MATCH(85,exp_wishno,0)))) | H91: =IF($A91="","",IF(INDEX(exp_fact,MATCH(85,exp_wishno,0))="","",INDEX(exp_fact,MATCH(85,exp_wishno,0)))) | I91: =IF($A91="","",IF(INDEX(exp_status,MATCH(85,exp_wishno,0))="","",INDEX(exp_status,MATCH(85,exp_wishno,0))))
A92: =IF(ISNA(MATCH(86,exp_wishno,0)),"",86) | B92: =IF($A92="","",IF(INDEX(exp_desc,MATCH(86,exp_wishno,0))="","",INDEX(exp_desc,MATCH(86,exp_wishno,0)))) | C92: =IF($A92="","",IF(INDEX(exp_cat,MATCH(86,exp_wishno,0))="","",INDEX(exp_cat,MATCH(86,exp_wishno,0)))) | D92: =IF($A92="","",IF(INDEX(exp_prio,MATCH(86,exp_wishno,0))="","",INDEX(exp_prio,MATCH(86,exp_wishno,0)))) | E92: =IF($A92="","",IF(INDEX(exp_year,MATCH(86,exp_wishno,0))="","",INDEX(exp_year,MATCH(86,exp_wishno,0)))) | F92: =IF($A92="","",IF(INDEX(exp_month,MATCH(86,exp_wishno,0))="","",INDEX(exp_month,MATCH(86,exp_wishno,0)))) | G92: =IF($A92="","",IF(INDEX(exp_plan,MATCH(86,exp_wishno,0))="","",INDEX(exp_plan,MATCH(86,exp_wishno,0)))) | H92: =IF($A92="","",IF(INDEX(exp_fact,MATCH(86,exp_wishno,0))="","",INDEX(exp_fact,MATCH(86,exp_wishno,0)))) | I92: =IF($A92="","",IF(INDEX(exp_status,MATCH(86,exp_wishno,0))="","",INDEX(exp_status,MATCH(86,exp_wishno,0))))
A93: =IF(ISNA(MATCH(87,exp_wishno,0)),"",87) | B93: =IF($A93="","",IF(INDEX(exp_desc,MATCH(87,exp_wishno,0))="","",INDEX(exp_desc,MATCH(87,exp_wishno,0)))) | C93: =IF($A93="","",IF(INDEX(exp_cat,MATCH(87,exp_wishno,0))="","",INDEX(exp_cat,MATCH(87,exp_wishno,0)))) | D93: =IF($A93="","",IF(INDEX(exp_prio,MATCH(87,exp_wishno,0))="","",INDEX(exp_prio,MATCH(87,exp_wishno,0)))) | E93: =IF($A93="","",IF(INDEX(exp_year,MATCH(87,exp_wishno,0))="","",INDEX(exp_year,MATCH(87,exp_wishno,0)))) | F93: =IF($A93="","",IF(INDEX(exp_month,MATCH(87,exp_wishno,0))="","",INDEX(exp_month,MATCH(87,exp_wishno,0)))) | G93: =IF($A93="","",IF(INDEX(exp_plan,MATCH(87,exp_wishno,0))="","",INDEX(exp_plan,MATCH(87,exp_wishno,0)))) | H93: =IF($A93="","",IF(INDEX(exp_fact,MATCH(87,exp_wishno,0))="","",INDEX(exp_fact,MATCH(87,exp_wishno,0)))) | I93: =IF($A93="","",IF(INDEX(exp_status,MATCH(87,exp_wishno,0))="","",INDEX(exp_status,MATCH(87,exp_wishno,0))))
A94: =IF(ISNA(MATCH(88,exp_wishno,0)),"",88) | B94: =IF($A94="","",IF(INDEX(exp_desc,MATCH(88,exp_wishno,0))="","",INDEX(exp_desc,MATCH(88,exp_wishno,0)))) | C94: =IF($A94="","",IF(INDEX(exp_cat,MATCH(88,exp_wishno,0))="","",INDEX(exp_cat,MATCH(88,exp_wishno,0)))) | D94: =IF($A94="","",IF(INDEX(exp_prio,MATCH(88,exp_wishno,0))="","",INDEX(exp_prio,MATCH(88,exp_wishno,0)))) | E94: =IF($A94="","",IF(INDEX(exp_year,MATCH(88,exp_wishno,0))="","",INDEX(exp_year,MATCH(88,exp_wishno,0)))) | F94: =IF($A94="","",IF(INDEX(exp_month,MATCH(88,exp_wishno,0))="","",INDEX(exp_month,MATCH(88,exp_wishno,0)))) | G94: =IF($A94="","",IF(INDEX(exp_plan,MATCH(88,exp_wishno,0))="","",INDEX(exp_plan,MATCH(88,exp_wishno,0)))) | H94: =IF($A94="","",IF(INDEX(exp_fact,MATCH(88,exp_wishno,0))="","",INDEX(exp_fact,MATCH(88,exp_wishno,0)))) | I94: =IF($A94="","",IF(INDEX(exp_status,MATCH(88,exp_wishno,0))="","",INDEX(exp_status,MATCH(88,exp_wishno,0))))
A95: =IF(ISNA(MATCH(89,exp_wishno,0)),"",89) | B95: =IF($A95="","",IF(INDEX(exp_desc,MATCH(89,exp_wishno,0))="","",INDEX(exp_desc,MATCH(89,exp_wishno,0)))) | C95: =IF($A95="","",IF(INDEX(exp_cat,MATCH(89,exp_wishno,0))="","",INDEX(exp_cat,MATCH(89,exp_wishno,0)))) | D95: =IF($A95="","",IF(INDEX(exp_prio,MATCH(89,exp_wishno,0))="","",INDEX(exp_prio,MATCH(89,exp_wishno,0)))) | E95: =IF($A95="","",IF(INDEX(exp_year,MATCH(89,exp_wishno,0))="","",INDEX(exp_year,MATCH(89,exp_wishno,0)))) | F95: =IF($A95="","",IF(INDEX(exp_month,MATCH(89,exp_wishno,0))="","",INDEX(exp_month,MATCH(89,exp_wishno,0)))) | G95: =IF($A95="","",IF(INDEX(exp_plan,MATCH(89,exp_wishno,0))="","",INDEX(exp_plan,MATCH(89,exp_wishno,0)))) | H95: =IF($A95="","",IF(INDEX(exp_fact,MATCH(89,exp_wishno,0))="","",INDEX(exp_fact,MATCH(89,exp_wishno,0)))) | I95: =IF($A95="","",IF(INDEX(exp_status,MATCH(89,exp_wishno,0))="","",INDEX(exp_status,MATCH(89,exp_wishno,0))))
A96: =IF(ISNA(MATCH(90,exp_wishno,0)),"",90) | B96: =IF($A96="","",IF(INDEX(exp_desc,MATCH(90,exp_wishno,0))="","",INDEX(exp_desc,MATCH(90,exp_wishno,0)))) | C96: =IF($A96="","",IF(INDEX(exp_cat,MATCH(90,exp_wishno,0))="","",INDEX(exp_cat,MATCH(90,exp_wishno,0)))) | D96: =IF($A96="","",IF(INDEX(exp_prio,MATCH(90,exp_wishno,0))="","",INDEX(exp_prio,MATCH(90,exp_wishno,0)))) | E96: =IF($A96="","",IF(INDEX(exp_year,MATCH(90,exp_wishno,0))="","",INDEX(exp_year,MATCH(90,exp_wishno,0)))) | F96: =IF($A96="","",IF(INDEX(exp_month,MATCH(90,exp_wishno,0))="","",INDEX(exp_month,MATCH(90,exp_wishno,0)))) | G96: =IF($A96="","",IF(INDEX(exp_plan,MATCH(90,exp_wishno,0))="","",INDEX(exp_plan,MATCH(90,exp_wishno,0)))) | H96: =IF($A96="","",IF(INDEX(exp_fact,MATCH(90,exp_wishno,0))="","",INDEX(exp_fact,MATCH(90,exp_wishno,0)))) | I96: =IF($A96="","",IF(INDEX(exp_status,MATCH(90,exp_wishno,0))="","",INDEX(exp_status,MATCH(90,exp_wishno,0))))
A97: =IF(ISNA(MATCH(91,exp_wishno,0)),"",91) | B97: =IF($A97="","",IF(INDEX(exp_desc,MATCH(91,exp_wishno,0))="","",INDEX(exp_desc,MATCH(91,exp_wishno,0)))) | C97: =IF($A97="","",IF(INDEX(exp_cat,MATCH(91,exp_wishno,0))="","",INDEX(exp_cat,MATCH(91,exp_wishno,0)))) | D97: =IF($A97="","",IF(INDEX(exp_prio,MATCH(91,exp_wishno,0))="","",INDEX(exp_prio,MATCH(91,exp_wishno,0)))) | E97: =IF($A97="","",IF(INDEX(exp_year,MATCH(91,exp_wishno,0))="","",INDEX(exp_year,MATCH(91,exp_wishno,0)))) | F97: =IF($A97="","",IF(INDEX(exp_month,MATCH(91,exp_wishno,0))="","",INDEX(exp_month,MATCH(91,exp_wishno,0)))) | G97: =IF($A97="","",IF(INDEX(exp_plan,MATCH(91,exp_wishno,0))="","",INDEX(exp_plan,MATCH(91,exp_wishno,0)))) | H97: =IF($A97="","",IF(INDEX(exp_fact,MATCH(91,exp_wishno,0))="","",INDEX(exp_fact,MATCH(91,exp_wishno,0)))) | I97: =IF($A97="","",IF(INDEX(exp_status,MATCH(91,exp_wishno,0))="","",INDEX(exp_status,MATCH(91,exp_wishno,0))))
A98: =IF(ISNA(MATCH(92,exp_wishno,0)),"",92) | B98: =IF($A98="","",IF(INDEX(exp_desc,MATCH(92,exp_wishno,0))="","",INDEX(exp_desc,MATCH(92,exp_wishno,0)))) | C98: =IF($A98="","",IF(INDEX(exp_cat,MATCH(92,exp_wishno,0))="","",INDEX(exp_cat,MATCH(92,exp_wishno,0)))) | D98: =IF($A98="","",IF(INDEX(exp_prio,MATCH(92,exp_wishno,0))="","",INDEX(exp_prio,MATCH(92,exp_wishno,0)))) | E98: =IF($A98="","",IF(INDEX(exp_year,MATCH(92,exp_wishno,0))="","",INDEX(exp_year,MATCH(92,exp_wishno,0)))) | F98: =IF($A98="","",IF(INDEX(exp_month,MATCH(92,exp_wishno,0))="","",INDEX(exp_month,MATCH(92,exp_wishno,0)))) | G98: =IF($A98="","",IF(INDEX(exp_plan,MATCH(92,exp_wishno,0))="","",INDEX(exp_plan,MATCH(92,exp_wishno,0)))) | H98: =IF($A98="","",IF(INDEX(exp_fact,MATCH(92,exp_wishno,0))="","",INDEX(exp_fact,MATCH(92,exp_wishno,0)))) | I98: =IF($A98="","",IF(INDEX(exp_status,MATCH(92,exp_wishno,0))="","",INDEX(exp_status,MATCH(92,exp_wishno,0))))
A99: =IF(ISNA(MATCH(93,exp_wishno,0)),"",93) | B99: =IF($A99="","",IF(INDEX(exp_desc,MATCH(93,exp_wishno,0))="","",INDEX(exp_desc,MATCH(93,exp_wishno,0)))) | C99: =IF($A99="","",IF(INDEX(exp_cat,MATCH(93,exp_wishno,0))="","",INDEX(exp_cat,MATCH(93,exp_wishno,0)))) | D99: =IF($A99="","",IF(INDEX(exp_prio,MATCH(93,exp_wishno,0))="","",INDEX(exp_prio,MATCH(93,exp_wishno,0)))) | E99: =IF($A99="","",IF(INDEX(exp_year,MATCH(93,exp_wishno,0))="","",INDEX(exp_year,MATCH(93,exp_wishno,0)))) | F99: =IF($A99="","",IF(INDEX(exp_month,MATCH(93,exp_wishno,0))="","",INDEX(exp_month,MATCH(93,exp_wishno,0)))) | G99: =IF($A99="","",IF(INDEX(exp_plan,MATCH(93,exp_wishno,0))="","",INDEX(exp_plan,MATCH(93,exp_wishno,0)))) | H99: =IF($A99="","",IF(INDEX(exp_fact,MATCH(93,exp_wishno,0))="","",INDEX(exp_fact,MATCH(93,exp_wishno,0)))) | I99: =IF($A99="","",IF(INDEX(exp_status,MATCH(93,exp_wishno,0))="","",INDEX(exp_status,MATCH(93,exp_wishno,0))))
A100: =IF(ISNA(MATCH(94,exp_wishno,0)),"",94) | B100: =IF($A100="","",IF(INDEX(exp_desc,MATCH(94,exp_wishno,0))="","",INDEX(exp_desc,MATCH(94,exp_wishno,0)))) | C100: =IF($A100="","",IF(INDEX(exp_cat,MATCH(94,exp_wishno,0))="","",INDEX(exp_cat,MATCH(94,exp_wishno,0)))) | D100: =IF($A100="","",IF(INDEX(exp_prio,MATCH(94,exp_wishno,0))="","",INDEX(exp_prio,MATCH(94,exp_wishno,0)))) | E100: =IF($A100="","",IF(INDEX(exp_year,MATCH(94,exp_wishno,0))="","",INDEX(exp_year,MATCH(94,exp_wishno,0)))) | F100: =IF($A100="","",IF(INDEX(exp_month,MATCH(94,exp_wishno,0))="","",INDEX(exp_month,MATCH(94,exp_wishno,0)))) | G100: =IF($A100="","",IF(INDEX(exp_plan,MATCH(94,exp_wishno,0))="","",INDEX(exp_plan,MATCH(94,exp_wishno,0)))) | H100: =IF($A100="","",IF(INDEX(exp_fact,MATCH(94,exp_wishno,0))="","",INDEX(exp_fact,MATCH(94,exp_wishno,0)))) | I100: =IF($A100="","",IF(INDEX(exp_status,MATCH(94,exp_wishno,0))="","",INDEX(exp_status,MATCH(94,exp_wishno,0))))
A101: =IF(ISNA(MATCH(95,exp_wishno,0)),"",95) | B101: =IF($A101="","",IF(INDEX(exp_desc,MATCH(95,exp_wishno,0))="","",INDEX(exp_desc,MATCH(95,exp_wishno,0)))) | C101: =IF($A101="","",IF(INDEX(exp_cat,MATCH(95,exp_wishno,0))="","",INDEX(exp_cat,MATCH(95,exp_wishno,0)))) | D101: =IF($A101="","",IF(INDEX(exp_prio,MATCH(95,exp_wishno,0))="","",INDEX(exp_prio,MATCH(95,exp_wishno,0)))) | E101: =IF($A101="","",IF(INDEX(exp_year,MATCH(95,exp_wishno,0))="","",INDEX(exp_year,MATCH(95,exp_wishno,0)))) | F101: =IF($A101="","",IF(INDEX(exp_month,MATCH(95,exp_wishno,0))="","",INDEX(exp_month,MATCH(95,exp_wishno,0)))) | G101: =IF($A101="","",IF(INDEX(exp_plan,MATCH(95,exp_wishno,0))="","",INDEX(exp_plan,MATCH(95,exp_wishno,0)))) | H101: =IF($A101="","",IF(INDEX(exp_fact,MATCH(95,exp_wishno,0))="","",INDEX(exp_fact,MATCH(95,exp_wishno,0)))) | I101: =IF($A101="","",IF(INDEX(exp_status,MATCH(95,exp_wishno,0))="","",INDEX(exp_status,MATCH(95,exp_wishno,0))))
...

Sheet 📚 Справочник
A1: 📚 Справочник
A2: Здесь живут все выпадающие списки. Добавляйте свои статьи в пустые жёлтые строки — они сразу появятся в списках листов «Расходы» и «Доходы».
D3: Категория с «Да» автоматически попадает в лист «✨ Хотелки»
A4: 📆 Год | B4: 🗓 Месяц | D4: 🏷 Категория расхода | E4: ✨ В список хотелок? | F4: 💬 Пояснение | H4: 📝 Статьи расходов | J4: 💼 Тип дохода | L4: 💰 Источники дохода | N4: 🚦 Статус расхода | O4: 🚦 Статус дохода | Q4: 🎯 Приоритет
A5: 2026 | B5: Январь | D5: 🛒 Нужда | E5: Нет | F5: Еда, жильё, транспорт — без этого никак | H5: Продукты | J5: 💼 Зарплата | L5: Основная работа | N5: ⏳ Запланировано | O5: ⏳ Ожидается | Q5: 🔥 Высокий
A6: 2027 | B6: Февраль | D6: 🧾 Обязательный платёж | E6: Нет | F6: Кредиты, налоги, страховки, подписки | H6: Аренда / ипотека | J6: 🚀 Проект | L6: Фриланс-проект | N6: ✅ Выполнено | O6: ✅ Получено | Q6: ⭐ Средний
A7: 2028 | B7: Март | D7: 🍭 Хотелка | E7: Да | F7: Маленькие радости «хочу прямо сейчас» | H7: Коммунальные услуги | J7: 🛠 Разовая услуга | L7: Консультация | N7: ⏸ Отложено | O7: ❌ Не получено | Q7: 💤 Низкий
A8: 2029 | B8: Апрель | D8: 💫 Желание | E8: Да | F8: Крупнее хотелки, стоит накопить | H8: Транспорт / такси | J8: 📈 Инвестиции | L8: Дивиденды | N8: ❌ Отменено
A9: 2030 | B9: Май | D9: 🌟 Мечта | E9: Да | F9: Большая цель: путешествие, машина, квартира | H9: Связь и интернет | J9: 🏆 Премия / бонус | L9: Кэшбэк
B10: Июнь | D10: 🎁 Подарок | E10: Нет | F10: Подарки близким | H10: Одежда | J10: 🏠 Аренда | L10: Подработка
B11: Июль | D11: 🏦 Накопление | E11: Нет | F11: Подушка безопасности, депозит | H11: Кафе и рестораны | J11: 🎁 Подарок
B12: Август | D12: 📈 Инвестиция | E12: Нет | F12: Акции, бизнес, активы | H12: Путешествия | J12: 💡 Прочее
B13: Сентябрь | D13: ❤️ Здоровье | E13: Нет | F13: Врачи, спорт, лекарства | H13: Техника
B14: Октябрь | D14: 🎓 Образование | E14: Нет | F14: Курсы, книги, обучение | H14: Подушка безопасности
B15: Ноябрь | D15: 🎉 Развлечения | E15: Нет | F15: Кафе, кино, отдых | H15: Подарки
B16: Декабрь | H16: Спорт
H17: Курсы
